MDIO/probador.v
 //Probador
 `timescale 1ns/1ns
 module probador (
 output reg clk, 
 output reg RESET,
 output reg MDIO_START,
 output reg MDIO,
 output reg MDIO_IN,
 output reg [31:0] T_DATA,
 input [15:0] RD_DATA, //bus de 16 bits para la salida Q 
 input MDIO_OUT,
 input MDIO_OE,
 input DATA_RDY,
 input MDC);

   
 

 initial begin
 //$monitor ("Q=%b,RCO=%b,D=%b,modo=%b", Q,RCO,D,modo);
 clk = 0;
 T_DATA = 32'b10000100010000001000010001000000;
 RESET = 0;
 #2 RESET = 1;
 #20 $finish;
 end
 
 always begin
  #1  clk =  ! clk;
 end



 endmodule

MDIO/MDIO.v
module MDIO  (  
    MDIO_OUT,
    MDIO_OE,
    DATA_RDY ,
    MDC,
    RD_DATA,//[15:0]
    clk, 
    MDC,  
    RESET,
    MDIO_START,
    MDIO,
    MDIO_IN,
    T_DATA //[31:0]
 );

  //------------Inputs--------------
    input clk, RESET, MDIO_START, MDIO, MDIO_IN;
    input [31:0] T_DATA;
  //----------Outputs--------------
    output reg [15:0] RD_DATA ; 
    output reg MDIO_OUT, MDIO_OE, DATA_RDY;
    output reg MDC;
    //------------variables auxiliares--------
    integer i=31; 
    integer j=31;
    integer a=0;
    reg [5:0] state;
    reg [5:0] nxt_state;
    reg modo;



always @(posedge clk) begin //flipflops de la maquina de estado 
  if (RESET) begin
     state  <= nxt_state;  // Estado de IDLE
  end else begin
    state  <= 6'b000001;   
  end
end 


  always @(posedge clk or posedge MDIO_START ) begin // procedimiento de las salidas y entradas del moculo 
          
      if(RESET) begin
      
        MDC <= ~MDC;

        if(modo)begin 
            //MDIO_START
            if(i==0) begin
                MDIO_OUT <= MDIO_OUT;
                MDIO_OE <= 0; 
            end else begin
                MDIO_OE <= 1;
                MDIO_OUT <= T_DATA[i]; 
                i = i-1;
            end

        end else if (modo==1'b0)begin
            
               if(j==15)begin
                  MDIO_OE <= 0;
                  MDIO_OUT<=MDIO_OUT;
                  RD_DATA [a] <= MDIO_IN; 
                  a = a+1;
               end else begin
                   MDIO_OE <= 1; 
                   MDIO_OUT <= T_DATA[j]; 
                  j = j-1;
               end

        end
    
      end
      else begin  
         MDC <= 0;
         i<=31; 
         j<=31;
         a<=0;
         DATA_RDY = 0;
         modo = 1'dx;

      end

    
  
  end


  always @(*) begin
    
    nxt_state = state;
    
    case(state) 

      6'b000001: if (T_DATA[31:30]==2'b01) nxt_state = 6'b000010;  
    
      else nxt_state = 6'b000001;   
                                        
      6'b000010: begin if (T_DATA[29:28]==(2'b01||2'b10)) begin 
        nxt_state = 6'b000100;  //write/read
          if(T_DATA[29:28]==2'b01)
              modo = 1; //modo write
          else modo = 0;  // modo read
        end
          else nxt_state = 6'b000010;
      end

      6'b000100:  nxt_state = 6'b001000;  //phyadr 

      6'b001000:  nxt_state = 6'b010000;  //regadr

      6'b010000:  nxt_state = 6'b100000; //ta

      6'b100000:  nxt_state = 6'b000010; //data

      default: nxt_state = 6'b000001;

    endcase

    end



endmodule

MDIO/tarea3testbench.v
 // Se incluyen lo otros modulos 
 
 
 `include "MDIO.v"
 `include "probador.v"

module tarea3testbench;

wire clk;
wire RESET;
wire MDIO_START;
wire MDIO;
wire MDIO_IN;
wire [31:0] T_DATA;
wire [15:0] RD_DATA; //bus de 16 bits para la salida Q 
wire MDIO_OUT;
wire MDIO_OE;
wire DATA_RDY;
wire MDC;

//se genera el archivo gtkwave
initial begin

  $dumpfile("resultados.vcd");
  $dumpvars;
  

end

// modulo

  MDIO M0 (
  .clk (clk),
  .RESET (RESET),
  .MDIO_START (MDIO_START), 
  .MDIO (MDIO),
  .MDIO_IN (MDIO_IN),
  .T_DATA (T_DATA),
  .RD_DATA (RD_DATA),
  .MDIO_OUT (MDIO_OUT),
  .MDIO_OE (MDIO_OE),
  .DATA_RDY (DATA_RDY),
  .MDC (MDC)
  );

 probador senales (
  .clk (clk),
  .RESET (RESET),
  .MDIO_START (MDIO_START), 
  .MDIO (MDIO),
  .MDIO_IN (MDIO_IN),
  .T_DATA (T_DATA),
  .RD_DATA (RD_DATA),
  .MDIO_OUT (MDIO_OUT),
  .MDIO_OE (MDIO_OE),
  .DATA_RDY (DATA_RDY),
  .MDC (MDC)
  );
  
 endmodule

MDIO/resultados.vcd
$date
	Tue Oct  4 17:52:55 2022
$end
$version
	Icarus Verilog
$end
$timescale
	1ns
$end
$scope module tarea3testbench $end
$var wire 1 ! clk $end
$var wire 32 " T_DATA [31:0] $end
$var wire 1 # RESET $end
$var wire 16 $ RD_DATA [15:0] $end
$var wire 1 % MDIO_START $end
$var wire 1 & MDIO_OUT $end
$var wire 1 ' MDIO_OE $end
$var wire 1 ( MDIO_IN $end
$var wire 1 ) MDIO $end
$var wire 1 * MDC $end
$var wire 1 + DATA_RDY $end
$scope module M0 $end
$var wire 1 ! clk $end
$var wire 32 , T_DATA [31:0] $end
$var wire 1 # RESET $end
$var wire 1 % MDIO_START $end
$var wire 1 ( MDIO_IN $end
$var wire 1 ) MDIO $end
$var reg 1 + DATA_RDY $end
$var reg 1 * MDC $end
$var reg 1 ' MDIO_OE $end
$var reg 1 & MDIO_OUT $end
$var reg 16 - RD_DATA [15:0] $end
$var reg 1 . modo $end
$var reg 6 / nxt_state [5:0] $end
$var reg 6 0 state [5:0] $end
$var integer 32 1 a [31:0] $end
$var integer 32 2 i [31:0] $end
$var integer 32 3 j [31:0] $end
$upscope $end
$scope module senales $end
$var wire 1 + DATA_RDY $end
$var wire 1 * MDC $end
$var wire 1 ' MDIO_OE $end
$var wire 1 & MDIO_OUT $end
$var wire 16 4 RD_DATA [15:0] $end
$var reg 1 ) MDIO $end
$var reg 1 ( MDIO_IN $end
$var reg 1 % MDIO_START $end
$var reg 1 # RESET $end
$var reg 32 5 T_DATA [31:0] $end
$var reg 1 ! clk $end
$upscope $end
$upscope $end
$enddefinitions $end
#0
$dumpvars
b10000100010000001000010001000000 5
bx 4
b11111 3
b11111 2
b0 1
bx 0
b1 /
x.
bx -
b10000100010000001000010001000000 ,
x+
x*
x)
x(
x'
x&
x%
bx $
0#
b10000100010000001000010001000000 "
0!
$end
#1
0*
b1 0
0+
1!
#2
0!
1#
#3
1*
1!
#4
0!
#5
0*
1!
#6
0!
#7
1*
1!
#8
0!
#9
0*
1!
#10
0!
#11
1*
1!
#12
0!
#13
0*
1!
#14
0!
#15
1*
1!
#16
0!
#17
0*
1!
#18
0!
#19
1*
1!
#20
0!
#21
0*
1!
