MDIO/probador.v
 //Probador
 `timescale 1ns/1ns
 module probador (
 output reg clk, 
 output reg RESET,
 output reg MDIO_START,
 output reg MDIO_IN,
 output reg [31:0] T_DATA,
 input [15:0] RD_DATA, //bus de 16 bits para la salida Q 
 input MDIO_OUT,
 input MDIO_OE,
 input DATA_RDY,
 input MDC);

 initial begin
 //$monitor ("Q=%b,RCO=%b,D=%b,modo=%b", Q,RCO,D,modo);
 clk = 0;
 #2 T_DATA = 32'b01010100010000001000010001000000; //cadena para write
 #1 MDIO_START = 1; //flanco positivo que legitima la entrada en T_DATA
 #1 MDIO_START = 0;
 #2 RESET = 1;
 #100 
 #1 RESET = 0; // Se resetea el modulo 
 #2 T_DATA = 32'b01100101110010001000010001000000;//cadena para read 
 #1 MDIO_START = 1;//flanco positivo que legitima la entrada en T_DATA
 #1 MDIO_START = 0;
 #10 RESET = 1; 
 #20 MDIO_IN =1;//entrada serial en 1 los primeros 3 ciclos 
 #20 MDIO_IN =0; //entrada serial los demas ciclos 
 #100 $finish;

 end
 
 always begin //clock del modulo 
  #1  clk =  ! clk;
 end



 endmodule

MDIO/MDIO.v
module MDIO  (  
    MDIO_OUT,
    MDIO_OE,
    DATA_RDY ,
    MDC,
    RD_DATA,//[15:0]
    clk, 
    MDC,  
    RESET,
    MDIO_START,
    MDIO_IN,
    T_DATA //[31:0]
 );

  //------------Inputs--------------
    input clk, RESET, MDIO_START, MDIO_IN;
    input [31:0] T_DATA;
  //----------Outputs--------------
    output reg [15:0] RD_DATA ; 
    output reg MDIO_OUT, MDIO_OE, DATA_RDY;
    output reg MDC;
    //------------variables auxiliares--------
    integer i=31; 
    integer j=31;
    integer a=0;
    reg [5:0] state;
    reg [5:0] nxt_state;
    reg modo;//variable que determina si es escritura o lectura



always @(posedge clk) begin //flipflops de la maquina de estado 
  if (RESET) begin
     state  <= nxt_state;  
  end else begin
    state  <= 6'b000001;   
  end
end 


  always @(posedge clk or posedge MDIO_START ) begin // procedimiento de las salidas y entradas del moculo 
          
      if(RESET) begin
      
        MDC <= ~MDC; // MDC con la mitad de la frecuencia del clk 

        if(modo)begin  //si modo es 1 se da una operacion de escritura
          
            if(i<0) begin // termina la operacion de escritura
                MDIO_OUT <= MDIO_OUT;
                MDIO_OE <= 0; 
            end else begin
                MDIO_OE <= 1; //se mantiene en alto durante la escritura
                MDIO_OUT <= T_DATA[i]; //va asignando cada dato de la entrada paralela a la salida serial 
                i = i-1;
            end

        end else if (modo==1'b0)begin // si modo es 0 se entra en la operacion de lectura
            
               if(j==15)begin //comienza a leer lo que este en la entrada MDIO_IN
                  MDIO_OE <= 0;
                  MDIO_OUT<=MDIO_OUT;
                  RD_DATA [a] = MDIO_IN; 
                  a = a+1;
                  if(a==16) // cuando se haya recorrido todo los ultimos 16 bits se pone en alto DATA_RDY
                  begin
                  DATA_RDY = 1;
                  end
      
               end else begin // Pone los primeros 16 bits de T_DATA en MDIO_OUT
                   MDIO_OE <= 1; //Se pone en alto durante esta operacion
                   MDIO_OUT <= T_DATA[j]; 
                  j = j-1;
               end

        end
    
      end
      else begin  //reset de todas las salidas y variables auxiliares del modulo 
         MDC <= 0;
         i<=31; 
         j<=31;
         a<=0;
         DATA_RDY = 0;
         modo = 1'dx;//tiene que ser un valor X ya que si es 0 o 1 impide el funcionamiento correcto del modulo 
         MDIO_OUT = 0;
         MDIO_OE =0;

      end

    
  
  end


  always @(*) begin
    
    nxt_state = state; //inicializacion 
    
    case(state) //un case para pasar de estado en estado 

      6'b000001: if (T_DATA[31:30]==2'b01) nxt_state = 6'b000010;  //estado ST, solo cuando los primeros 2 bits son 01  se pasa al siguiente estado
    
      else nxt_state = 6'b000001;   //se queda en este estado si no se cumple con lo anterior
                                        
      
      6'b000010: if (T_DATA[29:28]==(2'b10)) begin // estado OP, determina si es una operacion de write o read.  
          //nxt_state = 6'b000100; 
              if (T_DATA[29:28]==2'b10) begin //operacion de read 
                modo = 0; // modo read
                //nxt_state = 6'b000100;  // 
               end
               nxt_state = 6'b000100;//pasa al siguiente estado 
      end else if(T_DATA[29:28]==2'b01) begin//operacion write
                modo = 1;//modo write
                nxt_state = 6'b000100;//pasa al siguiente estado
      end else nxt_state = 6'b000001;//sino se cumple lo anterior se devuelve al primer estado
          
      6'b000100:  nxt_state = 6'b001000;  //estado phyadr 

      6'b001000:  nxt_state = 6'b010000;  //estado regadr

      6'b010000:  nxt_state = 6'b100000; //estado ta

      6'b100000:  nxt_state = 6'b000001; //estado data, se pasa al primer estado para la proxima operacion 

      default: nxt_state = 6'b000001;// si no pasa nada se pasa la primer estado 


    endcase

    end



endmodule

MDIO/tarea3testbench.v
 // Se incluyen lo otros modulos 
 
 
 `include "MDIO.v"
 `include "probador.v"

module tarea3testbench;

wire clk;
wire RESET;
wire MDIO_START;
wire MDIO_IN;
wire [31:0] T_DATA;
wire [15:0] RD_DATA; 
wire MDIO_OUT;
wire MDIO_OE;
wire DATA_RDY;
wire MDC;

//se genera el archivo gtkwave
initial begin

  $dumpfile("resultados.vcd");
  $dumpvars;
  

end

// modulo MDIO

  MDIO M0 (
  .clk (clk),
  .RESET (RESET),
  .MDIO_START (MDIO_START), 
  .MDIO_IN (MDIO_IN),
  .T_DATA (T_DATA),
  .RD_DATA (RD_DATA),
  .MDIO_OUT (MDIO_OUT),
  .MDIO_OE (MDIO_OE),
  .DATA_RDY (DATA_RDY),
  .MDC (MDC)
  );
//Modulo tester 
 probador senales (
  .clk (clk),
  .RESET (RESET),
  .MDIO_START (MDIO_START), 
  .MDIO_IN (MDIO_IN),
  .T_DATA (T_DATA),
  .RD_DATA (RD_DATA),
  .MDIO_OUT (MDIO_OUT),
  .MDIO_OE (MDIO_OE),
  .DATA_RDY (DATA_RDY),
  .MDC (MDC)
  );
  
 endmodule

MDIO/resultados.vcd
$date
	Mon Oct 10 18:20:42 2022
$end
$version
	Icarus Verilog
$end
$timescale
	1ns
$end
$scope module tarea3testbench $end
$var wire 1 ! clk $end
$var wire 32 " T_DATA [31:0] $end
$var wire 1 # RESET $end
$var wire 16 $ RD_DATA [15:0] $end
$var wire 1 % MDIO_START $end
$var wire 1 & MDIO_OUT $end
$var wire 1 ' MDIO_OE $end
$var wire 1 ( MDIO_IN $end
$var wire 1 ) MDC $end
$var wire 1 * DATA_RDY $end
$scope module M0 $end
$var wire 1 ! clk $end
$var wire 32 + T_DATA [31:0] $end
$var wire 1 # RESET $end
$var wire 1 % MDIO_START $end
$var wire 1 ( MDIO_IN $end
$var reg 1 * DATA_RDY $end
$var reg 1 ) MDC $end
$var reg 1 ' MDIO_OE $end
$var reg 1 & MDIO_OUT $end
$var reg 16 , RD_DATA [15:0] $end
$var reg 1 - modo $end
$var reg 6 . nxt_state [5:0] $end
$var reg 6 / state [5:0] $end
$var integer 32 0 a [31:0] $end
$var integer 32 1 i [31:0] $end
$var integer 32 2 j [31:0] $end
$upscope $end
$scope module senales $end
$var wire 1 * DATA_RDY $end
$var wire 1 ) MDC $end
$var wire 1 ' MDIO_OE $end
$var wire 1 & MDIO_OUT $end
$var wire 16 3 RD_DATA [15:0] $end
$var reg 1 ( MDIO_IN $end
$var reg 1 % MDIO_START $end
$var reg 1 # RESET $end
$var reg 32 4 T_DATA [31:0] $end
$var reg 1 ! clk $end
$upscope $end
$upscope $end
$enddefinitions $end
#0
$dumpvars
bx 4
bx 3
b11111 2
b11111 1
b0 0
bx /
bx .
x-
bx ,
bx +
x*
x)
x(
x'
x&
x%
bx $
x#
bx "
0!
$end
#1
b1 .
0)
b1 /
0'
0&
0*
1!
#2
b10 .
0!
b1010100010000001000010001000000 "
b1010100010000001000010001000000 +
b1010100010000001000010001000000 4
#3
1!
1%
#4
0!
0%
#5
1!
#6
0!
1#
#7
b100 .
1-
1)
b10 /
1!
#8
0!
#9
b1000 .
1'
0)
b100 /
b11110 1
1!
#10
0!
#11
b10000 .
1&
1)
b1000 /
b11101 1
1!
#12
0!
#13
b100000 .
0&
0)
b10000 /
b11100 1
1!
#14
0!
#15
b1 .
1&
1)
b100000 /
b11011 1
1!
#16
0!
#17
b10 .
0&
0)
b1 /
b11010 1
1!
#18
0!
#19
b100 .
1&
1)
b10 /
b11001 1
1!
#20
0!
#21
b1000 .
0&
0)
b100 /
b11000 1
1!
#22
0!
#23
b10000 .
1)
b1000 /
b10111 1
1!
#24
0!
#25
b100000 .
0)
b10000 /
b10110 1
1!
#26
0!
#27
b1 .
1&
1)
b100000 /
b10101 1
1!
#28
0!
#29
b10 .
0&
0)
b1 /
b10100 1
1!
#30
0!
#31
b100 .
1)
b10 /
b10011 1
1!
#32
0!
#33
b1000 .
0)
b100 /
b10010 1
1!
#34
0!
#35
b10000 .
1)
b1000 /
b10001 1
1!
#36
0!
#37
b100000 .
0)
b10000 /
b10000 1
1!
#38
0!
#39
b1 .
1)
b100000 /
b1111 1
1!
#40
0!
#41
b10 .
1&
0)
b1 /
b1110 1
1!
#42
0!
#43
b100 .
0&
1)
b10 /
b1101 1
1!
#44
0!
#45
b1000 .
0)
b100 /
b1100 1
1!
#46
0!
#47
b10000 .
1)
b1000 /
b1011 1
1!
#48
0!
#49
b100000 .
0)
b10000 /
b1010 1
1!
#50
0!
#51
b1 .
1&
1)
b100000 /
b1001 1
1!
#52
0!
#53
b10 .
0&
0)
b1 /
b1000 1
1!
#54
0!
#55
b100 .
1)
b10 /
b111 1
1!
#56
0!
#57
b1000 .
0)
b100 /
b110 1
1!
#58
0!
#59
b10000 .
1&
1)
b1000 /
b101 1
1!
#60
0!
#61
b100000 .
0&
0)
b10000 /
b100 1
1!
#62
0!
#63
b1 .
1)
b100000 /
b11 1
1!
#64
0!
#65
b10 .
0)
b1 /
b10 1
1!
#66
0!
#67
b100 .
1)
b10 /
b1 1
1!
#68
0!
#69
b1000 .
0)
b100 /
b0 1
1!
#70
0!
#71
b10000 .
1)
b1000 /
b11111111111111111111111111111111 1
1!
#72
0!
#73
b100000 .
0'
0)
b10000 /
1!
#74
0!
#75
b1 .
1)
b100000 /
1!
#76
0!
#77
b10 .
0)
b1 /
1!
#78
0!
#79
b100 .
1)
b10 /
1!
#80
0!
#81
b1000 .
0)
b100 /
1!
#82
0!
#83
b10000 .
1)
b1000 /
1!
#84
0!
#85
b100000 .
0)
b10000 /
1!
#86
0!
#87
b1 .
1)
b100000 /
1!
#88
0!
#89
b10 .
0)
b1 /
1!
#90
0!
#91
b100 .
1)
b10 /
1!
#92
0!
#93
b1000 .
0)
b100 /
1!
#94
0!
#95
b10000 .
1)
b1000 /
1!
#96
0!
#97
b100000 .
0)
b10000 /
1!
#98
0!
#99
b1 .
1)
b100000 /
1!
#100
0!
#101
b10 .
0)
b1 /
1!
#102
0!
#103
b100 .
1)
b10 /
1!
#104
0!
#105
b1000 .
0)
b100 /
1!
#106
0!
#107
b10 .
b11111 1
b1 /
x-
1!
0#
#108
0!
#109
b10 .
1!
b1100101110010001000010001000000 "
b1100101110010001000010001000000 +
b1100101110010001000010001000000 4
#110
0!
1%
#111
1!
0%
#112
0!
#113
1!
#114
0!
#115
1!
#116
0!
#117
1!
#118
0!
#119
1!
#120
0!
#121
b100 .
0-
1)
b10 /
1!
1#
#122
0!
#123
b1000 .
1'
0)
b100 /
b11110 2
1!
#124
0!
#125
b10000 .
1&
1)
b1000 /
b11101 2
1!
#126
0!
#127
b100000 .
0)
b10000 /
b11100 2
1!
#128
0!
#129
b1 .
0&
1)
b100000 /
b11011 2
1!
#130
0!
#131
b10 .
0)
b1 /
b11010 2
1!
#132
0!
#133
b100 .
1&
1)
b10 /
b11001 2
1!
#134
0!
#135
b1000 .
0&
0)
b100 /
b11000 2
1!
#136
0!
#137
b10000 .
1&
1)
b1000 /
b10111 2
1!
#138
0!
#139
b100000 .
0)
b10000 /
b10110 2
1!
#140
0!
#141
b1 .
1)
b100000 /
b10101 2
1!
1(
#142
0!
#143
b10 .
0&
0)
b1 /
b10100 2
1!
#144
0!
#145
b100 .
1)
b10 /
b10011 2
1!
#146
0!
#147
b1000 .
1&
0)
b100 /
b10010 2
1!
#148
0!
#149
b10000 .
0&
1)
b1000 /
b10001 2
1!
#150
0!
#151
b100000 .
0)
b10000 /
b10000 2
1!
#152
0!
#153
b1 .
1)
b100000 /
b1111 2
1!
#154
0!
#155
b10 .
0'
0)
b1 /
b1 0
bx1 $
bx1 ,
bx1 3
1!
#156
0!
#157
b100 .
1)
b10 /
b10 0
bx11 $
bx11 ,
bx11 3
1!
#158
0!
#159
b1000 .
0)
b100 /
b11 0
bx111 $
bx111 ,
bx111 3
1!
#160
0!
#161
b10000 .
1)
b1000 /
b100 0
bx0111 $
bx0111 ,
bx0111 3
1!
0(
#162
0!
#163
b100000 .
0)
b10000 /
b101 0
bx00111 $
bx00111 ,
bx00111 3
1!
#164
0!
#165
b1 .
1)
b100000 /
b110 0
bx000111 $
bx000111 ,
bx000111 3
1!
#166
0!
#167
b10 .
0)
b1 /
b111 0
bx0000111 $
bx0000111 ,
bx0000111 3
1!
#168
0!
#169
b100 .
1)
b10 /
b1000 0
bx00000111 $
bx00000111 ,
bx00000111 3
1!
#170
0!
#171
b1000 .
0)
b100 /
b1001 0
bx000000111 $
bx000000111 ,
bx000000111 3
1!
#172
0!
#173
b10000 .
1)
b1000 /
b1010 0
bx0000000111 $
bx0000000111 ,
bx0000000111 3
1!
#174
0!
#175
b100000 .
0)
b10000 /
b1011 0
bx00000000111 $
bx00000000111 ,
bx00000000111 3
1!
#176
0!
#177
b1 .
1)
b100000 /
b1100 0
bx000000000111 $
bx000000000111 ,
bx000000000111 3
1!
#178
0!
#179
b10 .
0)
b1 /
b1101 0
bx0000000000111 $
bx0000000000111 ,
bx0000000000111 3
1!
#180
0!
#181
b100 .
1)
b10 /
b1110 0
bx00000000000111 $
bx00000000000111 ,
bx00000000000111 3
1!
#182
0!
#183
b1000 .
0)
b100 /
b1111 0
bx000000000000111 $
bx000000000000111 ,
bx000000000000111 3
1!
#184
0!
#185
b10000 .
1)
b1000 /
1*
b10000 0
b111 $
b111 ,
b111 3
1!
#186
0!
#187
b100000 .
0)
b10000 /
b10001 0
1!
#188
0!
#189
b1 .
1)
b100000 /
b10010 0
1!
#190
0!
#191
b10 .
0)
b1 /
b10011 0
1!
#192
0!
#193
b100 .
1)
b10 /
b10100 0
1!
#194
0!
#195
b1000 .
0)
b100 /
b10101 0
1!
#196
0!
#197
b10000 .
1)
b1000 /
b10110 0
1!
#198
0!
#199
b100000 .
0)
b10000 /
b10111 0
1!
#200
0!
#201
b1 .
1)
b100000 /
b11000 0
1!
#202
0!
#203
b10 .
0)
b1 /
b11001 0
1!
#204
0!
#205
b100 .
1)
b10 /
b11010 0
1!
#206
0!
#207
b1000 .
0)
b100 /
b11011 0
1!
#208
0!
#209
b10000 .
1)
b1000 /
b11100 0
1!
#210
0!
#211
b100000 .
0)
b10000 /
b11101 0
1!
#212
0!
#213
b1 .
1)
b100000 /
b11110 0
1!
#214
0!
#215
b10 .
0)
b1 /
b11111 0
1!
#216
0!
#217
b100 .
1)
b10 /
b100000 0
1!
#218
0!
#219
b1000 .
0)
b100 /
b100001 0
1!
#220
0!
#221
b10000 .
1)
b1000 /
b100010 0
1!
#222
0!
#223
b100000 .
0)
b10000 /
b100011 0
1!
#224
0!
#225
b1 .
1)
b100000 /
b100100 0
1!
#226
0!
#227
b10 .
0)
b1 /
b100101 0
1!
#228
0!
#229
b100 .
1)
b10 /
b100110 0
1!
#230
0!
#231
b1000 .
0)
b100 /
b100111 0
1!
#232
0!
#233
b10000 .
1)
b1000 /
b101000 0
1!
#234
0!
#235
b100000 .
0)
b10000 /
b101001 0
1!
#236
0!
#237
b1 .
1)
b100000 /
b101010 0
1!
#238
0!
#239
b10 .
0)
b1 /
b101011 0
1!
#240
0!
#241
b100 .
1)
b10 /
b101100 0
1!
#242
0!
#243
b1000 .
0)
b100 /
b101101 0
1!
#244
0!
#245
b10000 .
1)
b1000 /
b101110 0
1!
#246
0!
#247
b100000 .
0)
b10000 /
b101111 0
1!
#248
0!
#249
b1 .
1)
b100000 /
b110000 0
1!
#250
0!
#251
b10 .
0)
b1 /
b110001 0
1!
#252
0!
#253
b100 .
1)
b10 /
b110010 0
1!
#254
0!
#255
b1000 .
0)
b100 /
b110011 0
1!
#256
0!
#257
b10000 .
1)
b1000 /
b110100 0
1!
#258
0!
#259
b100000 .
0)
b10000 /
b110101 0
1!
#260
0!
#261
b1 .
1)
b100000 /
b110110 0
1!
