contador4bits/probador.v
 //Probador
 `timescale 1ns/1ns
 module probador (output reg clk, output reg enb,
 output reg [3:0] D, //output reg [7:0] D,
 output reg [1:0] modo,
 input [3:0] Q, //input [7:0] Q,
 input  RCO //input [1:0] RCO,
 //input [1:0] a
 );

 // se inicializan los valores y luego se les pone valores segun la cantidad de flancos crecientes. 
 initial begin
 //$monitor ("Q=%b,RCO=%b,D=%b,modo=%b", Q,RCO,D,modo);
 clk = 0;
 enb = 0;
 modo = 2'b0;
 D = 4'b0;
 #5 enb = 2'b1;
 #5 D = 4'b0000;
 #5 modo = 2'b11;
 #5 modo = 2'b00;
 #150 $finish;
 end
 //el clk se invierte cada 5 unidades de tiempo 
 always begin
  #5  clk =  ! clk;
 end



 endmodule

contador4bits/tarea1.v
module tarea1    (  
    
    Q ,//output del estado del contador
    RCO,// Ripple-Carry Out
    a,//variable auxiliar
    clk, //clock del modulo
    enb,  // enable del contador
    modo,  // input modo
    D //input de datos
 );

  //------------Inputs--------------
    input enb, clk;
    input [3:0] D;
    input [1:0] modo;
  //----------Outputs--------------
    output reg [3:0] Q ; 
    output reg RCO;
    output reg a;


  //usar case/switch para los 4 casos para modo
  
always @(posedge clk)begin
  if (enb) begin
    //usar case casos del contador
        
        case (modo)
          2'b00: Q <= Q+1; //counter positivo +1
          2'b01: Q <= Q-1; //counter negativo -1
          2'b10: Q <= Q-3; //counter negativo de 3 en 3
          2'b11: Q <= D; //counter paralelo de su entrada D 
          default: Q <= Q;
        endcase
        
      
     // if(modo == 2'b11)begin
         // RCO = 1'b1; 
     // end else begin
       //   RCO =1'b0;
      //end

      if(modo == 2'b11) //cuando modo = 11 se tiene que inicializar con todos los contadores por lo que tiene que clk para que se de el always en caso contrario es RCO
        begin
          a = clk;
        end
      else begin 
          a = RCO;
      end


      if(Q == 4'b1110 && modo == 2'b00 ) begin //cuenta ascendente +1

          RCO = 1'b1; // RCO = 1 si se rebasa la cuenta ascendente

      end else begin

          if(Q == 4'b0001 && modo == 2'b01 ) begin //cuenta descendente -1

            RCO = 1'b1;// RCO = 1 si se rebasa la cuenta descendente

          end else begin
          
            //se presenta 3 casos cuando se da el RCO = 1, como se tiene un retardo a la hora de tomar RCO como 1, se usan condiciones antes de la condicion real
            // ejemplo caso cuando Q=0000, para este caso se haria if(Q == 4'b0011) ya que por el retardo cuando Q =0000 no lo toma como RCO = 1 

            if((Q == 4'b0011 || Q == 4'b0101 || Q == 4'b0100) && modo == 2'b10) begin //cuenta descendente -3

              RCO = 1'b1;// RCO = 1 si se rebasa la cuenta descendente -3 (casos 0,1,2)

            end else begin 
              RCO = 1'b0; //si no se cumple ninguno de los casos anteriores RCO = 0 
            end
          
          end 


      end
  
  end


end


endmodule

contador16bits/tarea1tb.v
 // Testbench Code Goes here
 
 `include "tarea1.v"
 `include "probador.v"
module tarea1tb ();
wire clk; 
wire enb;
wire [3:0] D; //wire [1:0][3:0] D;
wire [1:0] modo;
wire [3:0] Q; //wire [1:0][3:0] Q;
wire RCO; //wire [1:0] RCO;
//wire [1:0] a;

initial begin

  $dumpfile("resultados.vcd");
  $dumpvars;
  

end



  tarea1 U0 (
  .clk (clk),
 .enb (enb),
  .D (D), //(D[0])
  .modo (modo),
 .Q (Q),//(Q[0])
  .RCO (RCO),//(RCO[0])
  .a(a)//(a[0])
  );

/*  tarea1 U1 (
  .clk (a[0]),
 .enb (enb),
  .D (D[1]),
  .modo (modo),
 .Q (Q[1]),
  .RCO (RCO[1]),
  .a(a[1])
  );*/

probador senales (
  .clk (clk),
 .enb (enb),
  .D (D), //D[1:0]
  .modo (modo),
 .Q (Q),//Q[1:0]
  .RCO (RCO)
  //.a(a[1:0]) //a[1:0]
  );
  
 endmodule

contador4bits/resultados.vcd
$date
	Tue Sep 13 09:07:28 2022
$end
$version
	Icarus Verilog
$end
$timescale
	1ns
$end
$scope module tarea1tb $end
$var wire 2 ! modo [1:0] $end
$var wire 1 " enb $end
$var wire 1 # clk $end
$var wire 1 $ a $end
$var wire 1 % RCO $end
$var wire 4 & Q [3:0] $end
$var wire 4 ' D [3:0] $end
$scope module U0 $end
$var wire 2 ( modo [1:0] $end
$var wire 1 " enb $end
$var wire 1 # clk $end
$var wire 4 ) D [3:0] $end
$var reg 4 * Q [3:0] $end
$var reg 1 % RCO $end
$var reg 1 $ a $end
$upscope $end
$scope module senales $end
$var wire 4 + Q [3:0] $end
$var wire 1 % RCO $end
$var reg 4 , D [3:0] $end
$var reg 1 # clk $end
$var reg 1 " enb $end
$var reg 2 - modo [1:0] $end
$upscope $end
$upscope $end
$enddefinitions $end
#0
$dumpvars
b0 -
b0 ,
bx +
bx *
b0 )
b0 (
b0 '
bx &
x%
x$
0#
0"
b0 !
$end
#5
0%
1#
1"
#10
0#
#15
b0 &
b0 *
b0 +
1$
1#
b11 !
b11 (
b11 -
#20
0#
b0 !
b0 (
b0 -
#25
b1 &
b1 *
b1 +
0$
1#
#30
0#
#35
b10 &
b10 *
b10 +
1#
#40
0#
#45
b11 &
b11 *
b11 +
1#
#50
0#
#55
b100 &
b100 *
b100 +
1#
#60
0#
#65
b101 &
b101 *
b101 +
1#
#70
0#
#75
b110 &
b110 *
b110 +
1#
#80
0#
#85
b111 &
b111 *
b111 +
1#
#90
0#
#95
b1000 &
b1000 *
b1000 +
1#
#100
0#
#105
b1001 &
b1001 *
b1001 +
1#
#110
0#
#115
b1010 &
b1010 *
b1010 +
1#
#120
0#
#125
b1011 &
b1011 *
b1011 +
1#
#130
0#
#135
b1100 &
b1100 *
b1100 +
1#
#140
0#
#145
b1101 &
b1101 *
b1101 +
1#
#150
0#
#155
b1110 &
b1110 *
b1110 +
1#
#160
0#
#165
b1111 &
b1111 *
b1111 +
1%
1#
