I2C_Receptor/probador.v
//probador
`timescale 1ns/1ns

module probador(
output reg clk,
output reg SCL,
output reg RESET,
output reg SDA_OUT,
output reg SDA_OE,
output reg [6:0] I2C_ADDR,
output reg [15:0] RD_DATA,
input [15:0] WR_DATA,
input SDA_IN
);


initial begin
clk=0;
SCL=0;
RESET=1;
SDA_OUT=1;
I2C_ADDR = 7'b0000010;
RD_DATA= 16'b0011010011111111;
//escritura
#5 SDA_OUT=0;
#1 SDA_OE=1;
#45
#1 SDA_OUT=1;
#2 SDA_OUT=0;
#14 SDA_OE=0;//68
#8 SDA_OE=1;//76
#24 SDA_OUT=1;
#2 SDA_OUT=0;
#30 SDA_OE=0;//132
#8 SDA_OE=1;//140
#56 SDA_OE=0;//196
#18 SDA_OUT=1;//214
#2 //SDA_OUT=0;
#10//226
//lectura
#2 SDA_OUT=0;
#1 SDA_OE=1;
#46//49
#1 SDA_OUT=1;
#2 SDA_OUT=0; //52
#14 SDA_OUT=1;//66
#1 SDA_OUT=0;//67
#7 SDA_OE=0;
#64 SDA_OUT =1;//138
#8 SDA_OUT=0;
#56
#8 
#56 
#18 SDA_OUT=1;
#2 
//RESET
#10
#2 SDA_OUT=0;
#1 SDA_OE=1;
#46
#1 SDA_OUT=1;
#2 SDA_OUT=0;
#14 SDA_OUT=1;//66
#1 SDA_OUT=0;//67
#7 SDA_OE=0;
#64 SDA_OUT =1;//138
#8 SDA_OUT=0;
#8 RESET=0;
#56 
#56 
#18 SDA_OUT=1;
#2 RESET=1;

#100 $finish;
end 


always begin
#4 SCL = !SCL;
end

always begin
#1 clk = !clk;
end

endmodule

I2C_Receptor/I2C.v
module I2C(
SDA_OUT,
SDA_OE,
SCL,
RD_DATA,//15bits
clk,
RESET,
SDA_IN,
I2C_ADDR,
WR_DATA//15bits

);

//-----------Inputs------------
input clk, RESET, SDA_OUT, SDA_OE, SCL;
input [15:0] RD_DATA;
input [6:0] I2C_ADDR;
//-----------outputs-----------
output reg [15:0] WR_DATA;
output reg SDA_IN;
//------------Variables auxiliares--------


reg [7:0] i2c; //variable de I2C_ADD con RNW
//integer i=7;//contador escritura
integer j=15;//contador escritura
integer k=7;//contador lectura
integer cont1=7;
integer cont2=0;
integer cont3=0;
reg [5:0] state;
reg [5:0] nxt_state;
reg cadena1;//habilita el guardar los bits de SDA_OUT en i2c 
reg cadena2;//habilita la lectura o escritura primeros 8 bits
reg cadena3;//habilita la lectura o escritura segundos 8 bits
reg c;//variable para detectar un flanco negativo
integer SDA_old=0;//contador 


always@(posedge clk)begin//flipflops maquina de estado y detector de flancos
	if(RESET)begin 
		
		state<= nxt_state;//cambiar de estado
			
		//SDA_old <= SDA_OUT;//valor viejo de SDA_OUT
		
		if(SDA_old==0) begin
		if(SDA_OUT==0) begin
			c<=1'b1;//flanco negativo
			SDA_old=SDA_old+1;//contador 
		end else c<=1'b0;//estado normal
		end else c<=1'b0;

	end else begin //reset de todas las salidas y variables auxiliares del modulo
		//restableces los valores para realizar una nueva transsacion
		j=15;
		k=7;
		cont1=7;
		cont2=0;
		cont3=0;
		cadena1=1'dx;//encargada de 
		cadena2=1'dx;//wr_data1
		cadena3=1'dx;//wr_data2
		SDA_IN=0;
		i2c=8'dx;
		state=6'b000001;
		nxt_state=6'b000001;
		WR_DATA=16'dx;
		SDA_old=0;
	end
end


always@(posedge SCL)begin//procedimiento de las salidas y entradas  del modulo
	
	if(RESET==1)begin
		if(cont1>-1)begin//si cont1 es menor a 8 
			if(cadena1)begin // si cadena1 esta habilitado haga lo de poner en i2c lo de SDA_OUT 
			  		 
						i2c[cont1]<=SDA_OUT;//se poner SDA_OUT en i2c	   	
				   		cont1=cont1-1;//cont1 toma de 7 a 0 hasta llegar a los 8 bits
				
					end else begin
					cont1=cont1;
					i2c=i2c;
				end
		end else if(i2c[0]==0) begin//escritura 
					
				SDA_IN=0;
				//escritura
				if(cont2<=7)begin//si cont2 es menor a 7 
					if(cadena2)begin // si cadena2 esta habilitado haga lo de poner en WR_DATA los primeros 8 bits seriales de SDA_OUT
						if(cont2==7)begin//implementacion para terminar la cuenta
							SDA_IN=1;//ACK
							WR_DATA[cont2]<= SDA_OUT;//se pone bit a bit de SDA_OUT en WR_DATA
							cont2=cont2+1;	//cont2 suma 1 para llegar a los 7 bits 
						end else begin
							WR_DATA[cont2]<= SDA_OUT;//se pone bit a bit de SDA_OUT en WR_DATA
							cont2=cont2+1;	//cont2 suma 1 para llegar a los 7 bits 
						end
					
					end else begin 
						cont2=cont2;
					end


				end else begin 
					SDA_IN=0;//se baja el ACK 
					if(cont2<=16)begin//si cont2 es menor a 16 
						if(cadena3)begin// si cadena3 esta habilitado haga lo de poner en WR_DATA los otros 8 bits seriales de SDA_OUT
							if(cont2==16)begin//implementacion para terminar la cuenta
								cont2=cont2+1;//cont2 suma 1 para llegar a los 16 bits
								SDA_IN=1;//ACK
							end else begin 	
								WR_DATA[cont2]<=SDA_OUT;//se pone bit a bit de SDA_OUT en WR_DATA
								cont2=cont2+1;	//cont2 suma 1 para llegar a los 16 bits						
							end
							
						end else begin
							cont2=cont2;
						end
					end else cont2<=cont2;
				
				end
					

									
			end else begin
				SDA_IN=0;
				if(i2c[0]==1)begin //lectura

					if(cont2!=9)begin //si cont2 no es 9 
						if(cadena2)begin// si cadena2 esta habilitado haga lo de poner en SDA_IN los primeros 8 bits de RD_DATA
							if(j==7)begin//implementacion para ir del numero mas significativo al menos 
								//SDA_IN=1;
								cont2=cont2+1;//cont2 suma 1 para llegar a los 8 bits 
							end else begin 
								SDA_IN=RD_DATA[j];//se pone los primeros 8 bits de RD_DATA en SDA_IN
								j=j-1;
								cont2=cont2+1;//cont2 suma 1 para llegar a los 8 bits 
							end
					end else begin 
						cont2=cont2+1;
					end

				end else begin 
					if(cont3<=8)begin//si cont3 no es 9 
						if(cadena3)begin// si cadena3 esta habilitado haga lo de poner en SDA_IN los otros 8 bits de RD_DATA
							if(k==-1)begin//implementacion para ir del numero mas significativo al menos 
								cont3=cont3+1;//cont2 suma 1 para llegar a los 8 bits 
							end else begin
								SDA_IN= RD_DATA[k];//se pone los otros 8 bits de RD_DATA en SDA_IN
								k=k-1;
								cont3=cont3+1;	//cont2 suma 1 para llegar a los 8 bits 					
							end
						
						end else begin
							cont3=cont3+1;
						end

					end 
				
				
				end
	
			end 
			


		end


		end 

end 
		
			




always @(*)begin

	nxt_state = state;//inicializacion
	
	case(state)//un case para pasar de estado en estado
		
		6'b000001: begin//1
			if(SCL==1 && c==1) nxt_state=6'b000010;//Condicion de inicio cuando se da un flanco negativo de SDA_OUT y SCL esta en 1
			else nxt_state=6'b000001;
		end
		
		6'b000010: begin cadena1=1;//se habilita el poner SDA_OUT en i2c
		nxt_state=6'b000100;//siguiente estado
		end

		6'b000100: if(cont1==-1) nxt_state=6'b001000;//si termina de poner todos los bits de i2c pase al siguiente estado 
			   else nxt_state=6'b000100;

		6'b001000: if(i2c[7:1]==I2C_ADDR) begin//si se cumple que la direccion dada de I2C es igual a la que tiene el receptor pase al siguiente estado 
				SDA_IN=1;//ACK
				cadena2=1;//habilitacion de la proxima etapa de lectura o escritura
				nxt_state= 6'b010000;//siguiente estado
		end else begin//si la dirrecion no es la misma se recetea el estado y las variables auxiliares para que se ponga otro dispositivo  
				//i=6;
				j=15;
				cont1=0;
				cadena1=1'dx;
			    cadena2=1'dx;
			    nxt_state=6'b001000;
		end

		6'b010000: begin if(i2c[0]==0)begin//si es escritura   
					if(cont2==8)begin//se leyeron todos los datos ?
						cadena3=1; //si se leyeron todos pase a la sigueinte etapa
						nxt_state=6'b100000;
					end else nxt_state=6'b010000;
				end else if(SDA_OUT==1 && cont2==9)begin// es lectura, se recibio un ack y ya se termino de escribir los datos ?
					cadena3=1;//si se escribieron todos pase a la sigueinte etapa
					nxt_state=6'b100000;
				end else nxt_state=6'b010000;


		end


		6'b100000: begin //20
			if(cont2==17 || (cont3==9))begin //se termino de leer o de escribir todos los datos 
				if(SCL==1&&SDA_OUT==1)begin//condicion de parada
					//i=6;//restableces los valores para realizar una nueva transsacion
					j=15;
					k=7;
					cont1=7;
					cont2=0;
					cont3=0;
					cadena1=1'dx;//habilitacion de i2c
					cadena2=1'dx;//habilitacion de lectura o escritura primeros 8 bits
					cadena3=1'dx;//habilitacion de lectura o escritura segundos 8 bits 
					SDA_IN=0;
					i2c=8'dx;//reset de i2c
					state=6'b000001;
					nxt_state=6'b000001;
					WR_DATA=16'dx;//reset de WR_DATA
					SDA_old=0;
				end

			end else  nxt_state=6'b100000;		

		end

		default: nxt_state=6'b000001;//si no pasa nada se pasa al primer estado
	endcase
	
end

endmodule

I2C_Receptor/tarea5testbench.v
//se incluyen los otros modulos

`include "I2C.v"
`include "probador.v"

module tarea5testbench;

wire clk;
wire SDA_IN;
wire RESET;
wire [6:0] I2C_ADDR;
wire [15:0] WR_DATA;
wire [15:0] RD_DATA;
wire SDA_OUT;
wire SDA_OE;
wire SCL;


//se genera el archivo gtkwave
initial begin

  $dumpfile("resultados.vcd");
  $dumpvars;
  

end


//Modulo I2C

I2C IO(
.clk(clk),
.RESET(RESET),
.SDA_IN(SDA_IN),
.I2C_ADDR(I2C_ADDR),
.WR_DATA(WR_DATA),
.RD_DATA(RD_DATA),
.SDA_OUT(SDA_OUT),
.SDA_OE(SDA_OE),
.SCL(SCL)
);

//modulo tester

probador senales(
.clk(clk),
.RESET(RESET),
.SDA_IN(SDA_IN),
.I2C_ADDR(I2C_ADDR),
.WR_DATA(WR_DATA),
.RD_DATA(RD_DATA),
.SDA_OUT(SDA_OUT),
.SDA_OE(SDA_OE),
.SCL(SCL)
);

endmodule

I2C_Receptor/resultados.vcd
$date
	Mon Oct 31 11:37:23 2022
$end
$version
	Icarus Verilog
$end
$timescale
	1ns
$end
$scope module tarea5testbench $end
$var wire 1 ! clk $end
$var wire 16 " WR_DATA [15:0] $end
$var wire 1 # SDA_OUT $end
$var wire 1 $ SDA_OE $end
$var wire 1 % SDA_IN $end
$var wire 1 & SCL $end
$var wire 1 ' RESET $end
$var wire 16 ( RD_DATA [15:0] $end
$var wire 7 ) I2C_ADDR [6:0] $end
$scope module IO $end
$var wire 1 ! clk $end
$var wire 1 # SDA_OUT $end
$var wire 1 $ SDA_OE $end
$var wire 1 & SCL $end
$var wire 1 ' RESET $end
$var wire 16 * RD_DATA [15:0] $end
$var wire 7 + I2C_ADDR [6:0] $end
$var reg 1 % SDA_IN $end
$var reg 16 , WR_DATA [15:0] $end
$var reg 1 - c $end
$var reg 1 . cadena1 $end
$var reg 1 / cadena2 $end
$var reg 1 0 cadena3 $end
$var reg 8 1 i2c [7:0] $end
$var reg 6 2 nxt_state [5:0] $end
$var reg 6 3 state [5:0] $end
$var integer 32 4 SDA_old [31:0] $end
$var integer 32 5 cont1 [31:0] $end
$var integer 32 6 cont2 [31:0] $end
$var integer 32 7 cont3 [31:0] $end
$var integer 32 8 j [31:0] $end
$var integer 32 9 k [31:0] $end
$upscope $end
$scope module senales $end
$var wire 1 % SDA_IN $end
$var wire 16 : WR_DATA [15:0] $end
$var reg 7 ; I2C_ADDR [6:0] $end
$var reg 16 < RD_DATA [15:0] $end
$var reg 1 ' RESET $end
$var reg 1 & SCL $end
$var reg 1 $ SDA_OE $end
$var reg 1 # SDA_OUT $end
$var reg 1 ! clk $end
$upscope $end
$upscope $end
$enddefinitions $end
#0
$dumpvars
b11010011111111 <
b10 ;
bx :
b111 9
b1111 8
b0 7
b0 6
b111 5
b0 4
bx 3
b1 2
bx 1
x0
x/
x.
x-
bx ,
b10 +
b11010011111111 *
b10 )
b11010011111111 (
1'
0&
x%
x$
1#
bx "
0!
$end
#1
0-
b1 3
1!
#2
0!
#3
1!
#4
0!
1&
#5
b10 2
1-
b1 4
1!
0#
#6
0!
1$
#7
b100 2
1.
0-
b10 3
1!
#8
b100 2
0!
0&
#9
b100 3
1!
#10
0!
#11
1!
#12
b0xxxxxxx 1
b110 5
0!
1&
#13
1!
#14
0!
#15
1!
#16
0!
0&
#17
1!
#18
0!
#19
1!
#20
b0xxxxxx 1
b101 5
0!
1&
#21
1!
#22
0!
#23
1!
#24
0!
0&
#25
1!
#26
0!
#27
1!
#28
b0xxxxx 1
b100 5
0!
1&
#29
1!
#30
0!
#31
1!
#32
0!
0&
#33
1!
#34
0!
#35
1!
#36
b0xxxx 1
b11 5
0!
1&
#37
1!
#38
0!
#39
1!
#40
0!
0&
#41
1!
#42
0!
#43
1!
#44
b0xxx 1
b10 5
0!
1&
#45
1!
#46
0!
#47
1!
#48
0!
0&
#49
1!
#50
0!
#51
1!
#52
b1xx 1
b1 5
0!
1#
1&
#53
1!
#54
0!
0#
#55
1!
#56
0!
0&
#57
1!
#58
0!
#59
1!
#60
b10x 1
b0 5
0!
1&
#61
1!
#62
0!
#63
1!
#64
0!
0&
#65
1!
#66
0!
#67
1!
#68
b100 1
b1000 2
b11111111111111111111111111111111 5
0!
1&
0$
#69
b10000 2
1/
1%
b1000 3
1!
#70
0!
#71
b10000 3
1!
#72
0!
0&
#73
1!
#74
0!
#75
1!
#76
bx0 "
bx0 ,
bx0 :
b1 6
0%
0!
1&
1$
#77
1!
#78
0!
#79
1!
#80
0!
0&
#81
1!
#82
0!
#83
1!
#84
bx00 "
bx00 ,
bx00 :
b10 6
0!
1&
#85
1!
#86
0!
#87
1!
#88
0!
0&
#89
1!
#90
0!
#91
1!
#92
bx000 "
bx000 ,
bx000 :
b11 6
0!
1&
#93
1!
#94
0!
#95
1!
#96
0!
0&
#97
1!
#98
0!
#99
1!
#100
bx1000 "
bx1000 ,
bx1000 :
b100 6
0!
1&
1#
#101
1!
#102
0!
0#
#103
1!
#104
0!
0&
#105
1!
#106
0!
#107
1!
#108
bx01000 "
bx01000 ,
bx01000 :
b101 6
0!
1&
#109
1!
#110
0!
#111
1!
#112
0!
0&
#113
1!
#114
0!
#115
1!
#116
bx001000 "
bx001000 ,
bx001000 :
b110 6
0!
1&
#117
1!
#118
0!
#119
1!
#120
0!
0&
#121
1!
#122
0!
#123
1!
#124
bx0001000 "
bx0001000 ,
bx0001000 :
b111 6
0!
1&
#125
1!
#126
0!
#127
1!
#128
0!
0&
#129
1!
#130
0!
#131
1!
#132
bx00001000 "
bx00001000 ,
bx00001000 :
b100000 2
10
b1000 6
1%
0!
1&
0$
#133
b100000 3
1!
#134
0!
#135
1!
#136
0!
0&
#137
1!
#138
0!
#139
1!
#140
bx000001000 "
bx000001000 ,
bx000001000 :
b1001 6
0%
0!
1&
1$
#141
1!
#142
0!
#143
1!
#144
0!
0&
#145
1!
#146
0!
#147
1!
#148
bx0000001000 "
bx0000001000 ,
bx0000001000 :
b1010 6
0!
1&
#149
1!
#150
0!
#151
1!
#152
0!
0&
#153
1!
#154
0!
#155
1!
#156
bx00000001000 "
bx00000001000 ,
bx00000001000 :
b1011 6
0!
1&
#157
1!
#158
0!
#159
1!
#160
0!
0&
#161
1!
#162
0!
#163
1!
#164
bx000000001000 "
bx000000001000 ,
bx000000001000 :
b1100 6
0!
1&
#165
1!
#166
0!
#167
1!
#168
0!
0&
#169
1!
#170
0!
#171
1!
#172
bx0000000001000 "
bx0000000001000 ,
bx0000000001000 :
b1101 6
0!
1&
#173
1!
#174
0!
#175
1!
#176
0!
0&
#177
1!
#178
0!
#179
1!
#180
bx00000000001000 "
bx00000000001000 ,
bx00000000001000 :
b1110 6
0!
1&
#181
1!
#182
0!
#183
1!
#184
0!
0&
#185
1!
#186
0!
#187
1!
#188
bx000000000001000 "
bx000000000001000 ,
bx000000000001000 :
b1111 6
0!
1&
#189
1!
#190
0!
#191
1!
#192
0!
0&
#193
1!
#194
0!
#195
1!
#196
b1000 "
b1000 ,
b1000 :
b10000 6
0!
1&
0$
#197
1!
#198
0!
#199
1!
#200
0!
0&
#201
1!
#202
0!
#203
1!
#204
1%
b10001 6
0!
1&
#205
1!
#206
0!
#207
1!
#208
0!
0&
#209
1!
#210
0!
#211
1!
#212
0%
0!
1&
#213
1!
#214
b0 4
bx "
bx ,
bx :
b1 2
b1 3
bx 1
x0
x/
x.
b0 6
b111 5
0!
1#
#215
1!
#216
0!
0&
#217
1!
#218
0!
#219
1!
#220
0!
1&
#221
1!
#222
0!
#223
1!
#224
0!
0&
#225
1!
#226
0!
#227
1!
#228
0!
0#
1&
#229
b10 2
1-
b1 4
1!
1$
#230
0!
#231
b100 2
1.
0-
b10 3
1!
#232
b100 2
0!
0&
#233
b100 3
1!
#234
0!
#235
1!
#236
b0xxxxxxx 1
b110 5
0!
1&
#237
1!
#238
0!
#239
1!
#240
0!
0&
#241
1!
#242
0!
#243
1!
#244
b0xxxxxx 1
b101 5
0!
1&
#245
1!
#246
0!
#247
1!
#248
0!
0&
#249
1!
#250
0!
#251
1!
#252
b0xxxxx 1
b100 5
0!
1&
#253
1!
#254
0!
#255
1!
#256
0!
0&
#257
1!
#258
0!
#259
1!
#260
b0xxxx 1
b11 5
0!
1&
#261
1!
#262
0!
#263
1!
#264
0!
0&
#265
1!
#266
0!
#267
1!
#268
b0xxx 1
b10 5
0!
1&
#269
1!
#270
0!
#271
1!
#272
0!
0&
#273
1!
#274
0!
#275
1!
#276
b1xx 1
b1 5
0!
1#
1&
#277
1!
#278
0!
0#
#279
1!
#280
0!
0&
#281
1!
#282
0!
#283
1!
#284
b10x 1
b0 5
0!
1&
#285
1!
#286
0!
#287
1!
#288
0!
0&
#289
1!
#290
0!
#291
1!
#292
b101 1
b1000 2
b11111111111111111111111111111111 5
0!
1&
1#
#293
1/
1%
b1000 3
b10000 2
1!
0#
#294
0!
#295
b10000 3
1!
#296
0!
0&
#297
1!
#298
0!
#299
1!
#300
b1 6
b1110 8
0%
0!
1&
0$
#301
1!
#302
0!
#303
1!
#304
0!
0&
#305
1!
#306
0!
#307
1!
#308
b10 6
b1101 8
0!
1&
#309
1!
#310
0!
#311
1!
#312
0!
0&
#313
1!
#314
0!
#315
1!
#316
b11 6
b1100 8
1%
0!
1&
#317
1!
#318
0!
#319
1!
#320
0!
0&
#321
1!
#322
0!
#323
1!
#324
b100 6
b1011 8
1%
0!
1&
#325
1!
#326
0!
#327
1!
#328
0!
0&
#329
1!
#330
0!
#331
1!
#332
b101 6
b1010 8
0%
0!
1&
#333
1!
#334
0!
#335
1!
#336
0!
0&
#337
1!
#338
0!
#339
1!
#340
b110 6
b1001 8
1%
0!
1&
#341
1!
#342
0!
#343
1!
#344
0!
0&
#345
1!
#346
0!
#347
1!
#348
b111 6
b1000 8
0%
0!
1&
#349
1!
#350
0!
#351
1!
#352
0!
0&
#353
1!
#354
0!
#355
1!
#356
b1000 6
b111 8
0!
1&
#357
1!
#358
0!
#359
1!
#360
0!
0&
#361
1!
#362
0!
#363
1!
#364
b100000 2
10
b1001 6
0!
1&
1#
#365
b100000 3
1!
#366
0!
#367
1!
#368
0!
0&
#369
1!
#370
0!
#371
1!
#372
b1 7
b110 9
1%
0!
1&
0#
#373
1!
#374
0!
#375
1!
#376
0!
0&
#377
1!
#378
0!
#379
1!
#380
b10 7
b101 9
1%
0!
1&
#381
1!
#382
0!
#383
1!
#384
0!
0&
#385
1!
#386
0!
#387
1!
#388
b11 7
b100 9
1%
0!
1&
#389
1!
#390
0!
#391
1!
#392
0!
0&
#393
1!
#394
0!
#395
1!
#396
b100 7
b11 9
1%
0!
1&
#397
1!
#398
0!
#399
1!
#400
0!
0&
#401
1!
#402
0!
#403
1!
#404
b101 7
b10 9
1%
0!
1&
#405
1!
#406
0!
#407
1!
#408
0!
0&
#409
1!
#410
0!
#411
1!
#412
b110 7
b1 9
1%
0!
1&
#413
1!
#414
0!
#415
1!
#416
0!
0&
#417
1!
#418
0!
#419
1!
#420
b111 7
b0 9
1%
0!
1&
#421
1!
#422
0!
#423
1!
#424
0!
0&
#425
1!
#426
0!
#427
1!
#428
b1000 7
b11111111111111111111111111111111 9
1%
0!
1&
#429
1!
#430
0!
#431
1!
#432
0!
0&
#433
1!
#434
0!
#435
1!
#436
b1001 7
0%
0!
1&
#437
1!
#438
0!
#439
1!
#440
0!
0&
#441
1!
#442
0!
#443
1!
#444
0!
1&
#445
1!
#446
0!
#447
1!
#448
0!
0&
#449
1!
#450
0!
#451
1!
#452
0!
1&
#453
1!
#454
0!
#455
1!
#456
0!
0&
#457
1!
#458
0!
#459
1!
#460
0!
1&
#461
1!
#462
0!
#463
1!
#464
0!
0&
#465
1!
#466
0!
#467
1!
#468
0!
1&
#469
1!
#470
0!
#471
1!
#472
0!
0&
#473
1!
#474
0!
#475
1!
#476
0!
1&
#477
1!
#478
0!
#479
1!
#480
0!
0&
#481
1!
#482
0!
#483
1!
#484
0!
1&
#485
1!
#486
0!
#487
1!
#488
0!
0&
#489
1!
#490
0!
#491
1!
#492
0!
1&
#493
1!
#494
0!
#495
1!
#496
0!
0&
#497
1!
#498
0!
#499
1!
#500
0!
1&
#501
1!
#502
0!
#503
1!
#504
0!
0&
#505
1!
#506
0!
#507
1!
#508
0!
1&
#509
1!
#510
b0 4
b1 2
b1 3
bx 1
x0
x/
x.
b0 7
b0 6
b111 5
b111 9
b1111 8
0!
1#
#511
1!
#512
0!
0&
#513
1!
#514
0!
#515
1!
#516
0!
1&
#517
1!
#518
0!
#519
1!
#520
0!
0&
#521
1!
#522
0!
#523
1!
#524
0!
0#
1&
#525
b10 2
1-
b1 4
1!
1$
#526
0!
#527
b100 2
1.
0-
b10 3
1!
#528
b100 2
0!
0&
#529
b100 3
1!
#530
0!
#531
1!
#532
b0xxxxxxx 1
b110 5
0!
1&
#533
1!
#534
0!
#535
1!
#536
0!
0&
#537
1!
#538
0!
#539
1!
#540
b0xxxxxx 1
b101 5
0!
1&
#541
1!
#542
0!
#543
1!
#544
0!
0&
#545
1!
#546
0!
#547
1!
#548
b0xxxxx 1
b100 5
0!
1&
#549
1!
#550
0!
#551
1!
#552
0!
0&
#553
1!
#554
0!
#555
1!
#556
b0xxxx 1
b11 5
0!
1&
#557
1!
#558
0!
#559
1!
#560
0!
0&
#561
1!
#562
0!
#563
1!
#564
b0xxx 1
b10 5
0!
1&
#565
1!
#566
0!
#567
1!
#568
0!
0&
#569
1!
#570
0!
#571
1!
#572
b1xx 1
b1 5
0!
1#
1&
#573
1!
#574
0!
0#
#575
1!
#576
0!
0&
#577
1!
#578
0!
#579
1!
#580
b10x 1
b0 5
0!
1&
#581
1!
#582
0!
#583
1!
#584
0!
0&
#585
1!
#586
0!
#587
1!
#588
b101 1
b1000 2
b11111111111111111111111111111111 5
0!
1&
1#
#589
1/
1%
b1000 3
b10000 2
1!
0#
#590
0!
#591
b10000 3
1!
#592
0!
0&
#593
1!
#594
0!
#595
1!
#596
b1 6
b1110 8
0%
0!
1&
0$
#597
1!
#598
0!
#599
1!
#600
0!
0&
#601
1!
#602
0!
#603
1!
#604
b10 6
b1101 8
0!
1&
#605
1!
#606
0!
#607
1!
#608
0!
0&
#609
1!
#610
0!
#611
1!
#612
b11 6
b1100 8
1%
0!
1&
#613
1!
#614
0!
#615
1!
#616
0!
0&
#617
1!
#618
0!
#619
1!
#620
b100 6
b1011 8
1%
0!
1&
#621
1!
#622
0!
#623
1!
#624
0!
0&
#625
1!
#626
0!
#627
1!
#628
b101 6
b1010 8
0%
0!
1&
#629
1!
#630
0!
#631
1!
#632
0!
0&
#633
1!
#634
0!
#635
1!
#636
b110 6
b1001 8
1%
0!
1&
#637
1!
#638
0!
#639
1!
#640
0!
0&
#641
1!
#642
0!
#643
1!
#644
b111 6
b1000 8
0%
0!
1&
#645
1!
#646
0!
#647
1!
#648
0!
0&
#649
1!
#650
0!
#651
1!
#652
b1000 6
b111 8
0!
1&
#653
1!
#654
0!
#655
1!
#656
0!
0&
#657
1!
#658
0!
#659
1!
#660
b100000 2
10
b1001 6
0!
1&
1#
#661
b100000 3
1!
#662
0!
#663
1!
#664
0!
0&
#665
1!
#666
0!
#667
1!
#668
b1 7
b110 9
1%
0!
1&
0#
#669
1!
#670
0!
#671
1!
#672
0!
0&
#673
1!
#674
0!
#675
1!
#676
0!
1&
0'
#677
b0 4
b1 2
b1 3
bx 1
0%
x0
x/
x.
b0 7
b0 6
b111 5
b111 9
b1111 8
1!
#678
0!
#679
1!
#680
0!
0&
#681
1!
#682
0!
#683
1!
#684
0!
1&
#685
1!
#686
0!
#687
1!
#688
0!
0&
#689
1!
#690
0!
#691
1!
#692
0!
1&
#693
1!
#694
0!
#695
1!
#696
0!
0&
#697
1!
#698
0!
#699
1!
#700
0!
1&
#701
1!
#702
0!
#703
1!
#704
0!
0&
#705
1!
#706
0!
#707
1!
#708
0!
1&
#709
1!
#710
0!
#711
1!
#712
0!
0&
#713
1!
#714
0!
#715
1!
#716
0!
1&
#717
1!
#718
0!
#719
1!
#720
0!
0&
#721
1!
#722
0!
#723
1!
#724
0!
1&
#725
1!
#726
0!
#727
1!
#728
0!
0&
#729
1!
#730
0!
#731
1!
#732
0!
1&
#733
1!
#734
0!
#735
1!
#736
0!
0&
#737
1!
#738
0!
#739
1!
#740
0!
1&
#741
1!
#742
0!
#743
1!
#744
0!
0&
#745
1!
#746
0!
#747
1!
#748
0!
1&
#749
1!
#750
0!
#751
1!
#752
0!
0&
#753
1!
#754
0!
#755
1!
#756
0!
1&
#757
1!
#758
0!
#759
1!
#760
0!
0&
#761
1!
#762
0!
#763
1!
#764
0!
1&
#765
1!
#766
0!
#767
1!
#768
0!
0&
#769
1!
#770
0!
#771
1!
#772
0!
1&
#773
1!
#774
0!
#775
1!
#776
0!
0&
#777
1!
#778
0!
#779
1!
#780
0!
1&
#781
1!
#782
0!
#783
1!
#784
0!
0&
#785
1!
#786
0!
#787
1!
#788
0!
1&
#789
1!
#790
0!
#791
1!
#792
0!
0&
#793
1!
#794
0!
#795
1!
#796
0!
1&
#797
1!
#798
0!
#799
1!
#800
0!
0&
#801
1!
#802
0!
#803
1!
#804
0!
1&
#805
1!
#806
0!
1#
#807
1!
#808
0!
1'
0&
#809
1!
#810
0!
#811
1!
#812
0!
1&
#813
1!
#814
0!
#815
1!
#816
0!
0&
#817
1!
#818
0!
#819
1!
#820
0!
1&
#821
1!
#822
0!
#823
1!
#824
0!
0&
#825
1!
#826
0!
#827
1!
#828
0!
1&
#829
1!
#830
0!
#831
1!
#832
0!
0&
#833
1!
#834
0!
#835
1!
#836
0!
1&
#837
1!
#838
0!
#839
1!
#840
0!
0&
#841
1!
#842
0!
#843
1!
#844
0!
1&
#845
1!
#846
0!
#847
1!
#848
0!
0&
#849
1!
#850
0!
#851
1!
#852
0!
1&
#853
1!
#854
0!
#855
1!
#856
0!
0&
#857
1!
#858
0!
#859
1!
#860
0!
1&
#861
1!
#862
0!
#863
1!
#864
0!
0&
#865
1!
#866
0!
#867
1!
#868
0!
1&
#869
1!
#870
0!
#871
1!
#872
0!
0&
#873
1!
#874
0!
#875
1!
#876
0!
1&
#877
1!
#878
0!
#879
1!
#880
0!
0&
#881
1!
#882
0!
#883
1!
#884
0!
1&
#885
1!
#886
0!
#887
1!
#888
0!
0&
#889
1!
#890
0!
#891
1!
#892
0!
1&
#893
1!
#894
0!
#895
1!
#896
0!
0&
#897
1!
#898
0!
#899
1!
#900
0!
1&
#901
1!
#902
0!
#903
1!
#904
0!
0&
#905
1!
#906
0!
#907
1!
#908
0!
1&
