I2C_Generador/probador.v
//probador
`timescale 1ns/1ns

module probador(
output reg clk,
output reg RESET,
output reg RNW,
output reg SDA_IN,
output reg START_STB,
output reg [15:0] WR_DATA,
output reg [6:0] I2C_ADDR,
input [15:0] RD_DATA,
input SDA_OUT,
input SDA_OE,
input SCL
);

initial begin
clk=0;
//escritura
RNW=0;
RESET=1;
WR_DATA = 16'b0000000011111111;
#18
#1 START_STB=1;
#1 START_STB=0;
#2 I2C_ADDR = 7'b0000010;
#63 SDA_IN=1;
#2 SDA_IN=0;
#26 
#10 
#43 SDA_IN=1;
#2 SDA_IN=0;
#70 SDA_IN=1;
#2 SDA_IN=0;
//lectura
#20 RNW=1;
#21 
#2 START_STB=1;
#1 START_STB=0;
#2 I2C_ADDR = 7'b0000010;
#63 SDA_IN=1;
#2 SDA_IN=0;
#26 SDA_IN=1;
#10 SDA_IN=0;
#43 SDA_IN=1;
#2 SDA_IN=0;
#100 SDA_IN=1;
#2 SDA_IN=0;
//reset
#20
#1 START_STB=1;
#1 START_STB=0;
#2 I2C_ADDR = 7'b0000010;
#63 SDA_IN=1;
#2 SDA_IN=0;
#26 SDA_IN=1;
#10 SDA_IN=0;
#43 SDA_IN=1;
#2 SDA_IN=0;
#30 RESET=0;
#10 RESET=1;
#30
$finish;
end 


always begin
#1 clk = !clk;
end

endmodule

I2C_Generador/I2C.v
module I2C(
SDA_OUT,
SDA_OE,
SCL,
RD_DATA,//15bits
clk,
RNW,
RESET,
SDA_IN,
I2C_ADDR,
START_STB,
WR_DATA//15bits

);

//-----------Inputs------------
input clk, RESET, RNW, SDA_IN, START_STB;
input [15:0] WR_DATA;
input [6:0] I2C_ADDR;
//-----------outputs-----------
output reg [15:0] RD_DATA;
output reg SDA_OUT, SDA_OE;
output SCL;
//------------Variables auxiliares--------
wire[7:0] rnw; //variable de I2C_ADD con RNW
integer i=6;//contador escritura
integer j=15;//contador escritura
integer k=7;//contador lectura
integer cont1=0;
integer cont2=0;
integer cont3=0;
reg [5:0] state;
reg [5:0] nxt_state;
reg cadena1;//I2C_ADDR
reg cadena2;//wr_data1
reg cadena3;//wr_data2
reg [1:0] m;//variable para SCL 25 % de la frecuencia de clk
reg c;//variable para detectar un flanco negativo
reg SDA_old;//variable para detectar un flanco negativo

assign rnw[7:1] = I2C_ADDR;
assign rnw[0]=RNW;
initial m=0;
initial SDA_OUT=1;

always@(posedge clk)begin//flipflops maquina de estado y detector de flancos
	if(RESET)begin 
		
		state<= nxt_state;
		m<=m+1;
		
		if(START_STB==1)begin
			SDA_OUT=0;
		end
	
		SDA_old<= SDA_OUT;
		begin
		if(~SDA_OUT && SDA_old)
			c<=1'b0;
		else c<=1'b1;

		end
	end else begin //reset de todas las salidas y variables auxiliares del modulo
		i=6;
		j=15;
		k=7;
		cont1=0;
		cont2=0;
		cont3=0;
		nxt_state<=6'b000001;
		cadena1=1'dx;//I2C_ADDR
		cadena2=1'dx;//wr_data1
		cadena3=1'dx;//wr_data2
		RD_DATA<=16'dx;
		SDA_OE <=0;
		SDA_OUT<=1;
	end
end

assign SCL = m[1];

always@(posedge SCL)begin//procedimiento de las salidas y entradas  del modulo
	
	if(RESET==1)begin
		if(cont1<=8)begin
			if(cadena1)begin
				   if(i==-1)begin
						SDA_OE=0;
				   		SDA_OUT=0;
				   		cont1=cont1+1;
				   end else begin
			 	   		SDA_OE=1;
				   		SDA_OUT=rnw[i];
				   		i=i-1;
				   		cont1=cont1+1;
				   end
			end else begin
					SDA_OE=SDA_OE;
					SDA_OUT=SDA_OUT;
				end
		end else begin
			if(RNW==0)begin //escritura

				if(cont2!=9)begin
					if(cadena2)begin
						if(j==7)begin
							SDA_OE=0;
							cont2=cont2+1;
						end else begin 
							SDA_OUT=WR_DATA[j];
				   			SDA_OE<=1;
							j=j-1;
							cont2=cont2+1;
						end
					end else begin 
						SDA_OE=SDA_OE;
				   		SDA_OUT=SDA_OUT;
					end

				end else begin 
					if(cont3!=9)begin
						if(cadena3)begin
							if(k==-1)begin
								SDA_OE=0;
								SDA_OUT=0;	
								cont3=cont3+1;
							end else begin
								SDA_OUT= WR_DATA[k];
								SDA_OE =1;
								k=k-1;
								cont3=cont3+1;						
							end
						
						end else begin
							SDA_OE=SDA_OE;
							SDA_OUT=SDA_OUT;
						end

					end else SDA_OE=0;
				
				
				end
	
			end else begin //lectura
				if(cont2<=7)begin
					if(cadena2)begin
						if(cont2==7)begin
							SDA_OE<=0;
							SDA_OUT<=1;
							RD_DATA[cont2]<= SDA_IN;
							cont2=cont2+1;
						end else begin
							RD_DATA[cont2]<= SDA_IN;
							SDA_OE<=0;
							cont2=cont2+1;
						end
					
					end else begin 
						SDA_OUT<=SDA_OUT;
						SDA_OE<=SDA_OUT;
					end


				end else begin 
					SDA_OUT=0;
					if(cont2<=16)begin
						if(cadena3)begin
							if(cont2==16)begin
								SDA_OE<=0;
								cont2=cont2+1;
							end else begin 	
								RD_DATA[cont2]<=SDA_IN;
								SDA_OE<=0;
								cont2=cont2+1;							
							end
							
						end else begin
							SDA_OE<=0;
							SDA_OUT <= SDA_OUT;
						end
					end else SDA_OE<=0;
				
				end
			


		end


	end
		
	end

end


always @(*)begin

	nxt_state = state;//inicializacion
	
	case(state)//un case para pasar de estado en estado
		
		6'b000001: begin//1
			if(SCL==1 && c==0) nxt_state=6'b000010;
			else nxt_state=6'b000001;
		end
		
		6'b000010: begin cadena1=1;//2
		nxt_state=6'b000100;
		end

		6'b000100: if(cont1==8) nxt_state=6'b001000;//4
			   else nxt_state=6'b000100;

		6'b001000: if(SDA_IN==1)begin//8
				cadena2=1;
				nxt_state= 6'b010000;
			   end else nxt_state=6'b001000;

		6'b010000: begin if(RNW==1)begin//10
					if(cont2==8)begin
						cadena3=1;
						nxt_state=6'b100000;
					end else nxt_state=6'b010000;
				end else if(SDA_IN==1 && cont2==9)begin
					cadena3=1;
					nxt_state=6'b100000;
				end else nxt_state=6'b010000;


		end


		6'b100000: begin //20
			if(cont2==17 || (cont3==9 && SDA_IN==1))begin 
				SDA_OUT=1;
				if(SDA_OUT==1 && SCL==1)begin
					i=6;//restableces los valores para realizar una nueva transsacion
					j=15;
					k=7;
					cont1=0;
					cont2=0;
					cont3=0;
					state=6'b000001;
					nxt_state=6'b000001;
					cadena1=1'dx;//I2C_ADDR
					cadena2=1'dx;//wr_data1
					cadena3=1'dx;//wr_data2
					RD_DATA<=16'dx;
					SDA_OE =0;
					SDA_OUT=1;
				end

			end else nxt_state=6'b100000;		

		end

		default: nxt_state=6'b000001;//si no pasa nada se pasa al primer estado
	endcase
	
end

endmodule

I2C_Generador/tarea3testbench.v
//se incluyen los otros modulos

`include "I2C.v"
`include "probador.v"

module tarea3testbench;

wire clk;
wire SDA_IN;
wire RESET;
wire RNW;
wire [6:0] I2C_ADDR;
wire START_STB;
wire [15:0] WR_DATA;
wire [15:0] RD_DATA;
wire SDA_OUT;
wire SDA_OE;
wire SCL;


//se genera el archivo gtkwave
initial begin

  $dumpfile("resultados.vcd");
  $dumpvars;
  

end


//Modulo I2C

I2C IO(
.clk(clk),
.RESET(RESET),
.SDA_IN(SDA_IN),
.RNW(RNW),
.START_STB(START_STB),
.I2C_ADDR(I2C_ADDR),
.WR_DATA(WR_DATA),
.RD_DATA(RD_DATA),
.SDA_OUT(SDA_OUT),
.SDA_OE(SDA_OE),
.SCL(SCL)
);

//modulo tester

probador senales(
.clk(clk),
.RESET(RESET),
.SDA_IN(SDA_IN),
.RNW(RNW),
.START_STB(START_STB),
.I2C_ADDR(I2C_ADDR),
.WR_DATA(WR_DATA),
.RD_DATA(RD_DATA),
.SDA_OUT(SDA_OUT),
.SDA_OE(SDA_OE),
.SCL(SCL)
);

endmodule

I2C_Generador/resultados.vcd
$date
	Fri Oct 21 23:52:31 2022
$end
$version
	Icarus Verilog
$end
$timescale
	1ns
$end
$scope module tarea3testbench $end
$var wire 1 ! clk $end
$var wire 16 " WR_DATA [15:0] $end
$var wire 1 # START_STB $end
$var wire 1 $ SDA_OUT $end
$var wire 1 % SDA_OE $end
$var wire 1 & SDA_IN $end
$var wire 1 ' SCL $end
$var wire 1 ( RNW $end
$var wire 1 ) RESET $end
$var wire 16 * RD_DATA [15:0] $end
$var wire 7 + I2C_ADDR [6:0] $end
$scope module IO $end
$var wire 8 , rnw [7:0] $end
$var wire 1 ! clk $end
$var wire 16 - WR_DATA [15:0] $end
$var wire 1 # START_STB $end
$var wire 1 & SDA_IN $end
$var wire 1 ' SCL $end
$var wire 1 ( RNW $end
$var wire 1 ) RESET $end
$var wire 7 . I2C_ADDR [6:0] $end
$var reg 16 / RD_DATA [15:0] $end
$var reg 1 % SDA_OE $end
$var reg 1 $ SDA_OUT $end
$var reg 1 0 SDA_old $end
$var reg 1 1 c $end
$var reg 1 2 cadena1 $end
$var reg 1 3 cadena2 $end
$var reg 1 4 cadena3 $end
$var reg 2 5 m [1:0] $end
$var reg 6 6 nxt_state [5:0] $end
$var reg 6 7 state [5:0] $end
$var integer 32 8 cont1 [31:0] $end
$var integer 32 9 cont2 [31:0] $end
$var integer 32 : cont3 [31:0] $end
$var integer 32 ; i [31:0] $end
$var integer 32 < j [31:0] $end
$var integer 32 = k [31:0] $end
$upscope $end
$scope module senales $end
$var wire 16 > RD_DATA [15:0] $end
$var wire 1 ' SCL $end
$var wire 1 % SDA_OE $end
$var wire 1 $ SDA_OUT $end
$var reg 7 ? I2C_ADDR [6:0] $end
$var reg 1 ) RESET $end
$var reg 1 ( RNW $end
$var reg 1 & SDA_IN $end
$var reg 1 # START_STB $end
$var reg 16 @ WR_DATA [15:0] $end
$var reg 1 ! clk $end
$upscope $end
$upscope $end
$enddefinitions $end
#0
$dumpvars
b11111111 @
bx ?
bx >
b111 =
b1111 <
b110 ;
b0 :
b0 9
b0 8
bx 7
b1 6
b0 5
x4
x3
x2
x1
x0
bx /
bx .
b11111111 -
bx0 ,
bx +
bx *
1)
0(
0'
x&
x%
1$
x#
b11111111 "
0!
$end
#1
11
10
b1 5
b1 7
1!
#2
0!
#3
1'
b10 5
1!
#4
0!
#5
b11 5
1!
#6
0!
#7
0'
b0 5
1!
#8
0!
#9
b1 5
1!
#10
0!
#11
1'
b10 5
1!
#12
0!
#13
b11 5
1!
#14
0!
#15
0'
b0 5
1!
#16
0!
#17
b1 5
1!
#18
0!
#19
b10 6
1'
01
00
b10 5
0$
1!
1#
#20
0!
0#
#21
b100 6
12
11
b11 5
b10 7
1!
#22
0!
b100 ,
b10 +
b10 .
b10 ?
#23
0'
b0 5
b100 7
1!
#24
0!
#25
b1 5
1!
#26
0!
#27
b1 8
b101 ;
1%
1'
b10 5
1!
#28
0!
#29
b11 5
1!
#30
0!
#31
0'
b0 5
1!
#32
0!
#33
b1 5
1!
#34
0!
#35
b10 8
b100 ;
1'
b10 5
1!
#36
0!
#37
b11 5
1!
#38
0!
#39
0'
b0 5
1!
#40
0!
#41
b1 5
1!
#42
0!
#43
b11 8
b11 ;
1'
b10 5
1!
#44
0!
#45
b11 5
1!
#46
0!
#47
0'
b0 5
1!
#48
0!
#49
b1 5
1!
#50
0!
#51
b100 8
b10 ;
1'
b10 5
1!
#52
0!
#53
b11 5
1!
#54
0!
#55
0'
b0 5
1!
#56
0!
#57
b1 5
1!
#58
0!
#59
b101 8
b1 ;
1$
1'
b10 5
1!
#60
0!
#61
10
b11 5
1!
#62
0!
#63
0'
b0 5
1!
#64
0!
#65
b1 5
1!
#66
0!
#67
b110 8
b0 ;
0$
1'
b10 5
1!
#68
0!
#69
01
00
b11 5
1!
#70
0!
#71
0'
11
b0 5
1!
#72
0!
#73
b1 5
1!
#74
0!
#75
b111 8
b11111111111111111111111111111111 ;
1'
b10 5
1!
#76
0!
#77
b11 5
1!
#78
0!
#79
0'
b0 5
1!
#80
0!
#81
b1 5
1!
#82
0!
#83
b1000 6
b1000 8
0%
1'
b10 5
1!
#84
0!
#85
13
b11 5
b1000 7
b10000 6
1!
1&
#86
0!
#87
0'
b0 5
b1000 6
1!
0&
#88
0!
#89
b1 5
1!
#90
0!
#91
b1001 8
1'
b10 5
1!
#92
0!
#93
b11 5
1!
#94
0!
#95
0'
b0 5
1!
#96
0!
#97
b1 5
1!
#98
0!
#99
1%
b1 9
b1110 <
1'
b10 5
1!
#100
0!
#101
b11 5
1!
#102
0!
#103
0'
b0 5
1!
#104
0!
#105
b1 5
1!
#106
0!
#107
b10 9
b1101 <
1'
b10 5
1!
#108
0!
#109
b11 5
1!
#110
0!
#111
0'
b0 5
1!
#112
0!
#113
b1 5
1!
#114
0!
#115
b11 9
b1100 <
1'
b10 5
1!
#116
0!
#117
b11 5
1!
#118
0!
#119
0'
b0 5
1!
#120
0!
#121
b1 5
1!
#122
0!
#123
b100 9
b1011 <
1'
b10 5
1!
#124
0!
#125
b11 5
1!
#126
0!
#127
0'
b0 5
1!
#128
0!
#129
b1 5
1!
#130
0!
#131
b101 9
b1010 <
1'
b10 5
1!
#132
0!
#133
b11 5
1!
#134
0!
#135
0'
b0 5
1!
#136
0!
#137
b1 5
1!
#138
0!
#139
b110 9
b1001 <
1'
b10 5
1!
#140
0!
#141
b11 5
1!
#142
0!
#143
0'
b0 5
1!
#144
0!
#145
b1 5
1!
#146
0!
#147
b111 9
b1000 <
1'
b10 5
1!
#148
0!
#149
b11 5
1!
#150
0!
#151
0'
b0 5
1!
#152
0!
#153
b1 5
1!
#154
0!
#155
b1000 9
b111 <
1'
b10 5
1!
#156
0!
#157
b11 5
1!
#158
0!
#159
0'
b0 5
1!
#160
0!
#161
b1 5
1!
#162
0!
#163
b1001 9
0%
1'
b10 5
1!
#164
0!
#165
b11 5
1!
#166
b10000 6
0!
1&
#167
0'
b100000 6
14
b0 5
b10000 7
1!
#168
b10000 6
0!
0&
#169
b1 5
1!
#170
0!
#171
b1 :
b110 =
1%
1$
1'
b10 5
1!
#172
0!
#173
10
b11 5
1!
#174
0!
#175
0'
b0 5
1!
#176
0!
#177
b1 5
1!
#178
0!
#179
b10 :
b101 =
1'
b10 5
1!
#180
0!
#181
b11 5
1!
#182
0!
#183
0'
b0 5
1!
#184
0!
#185
b1 5
1!
#186
0!
#187
b11 :
b100 =
1'
b10 5
1!
#188
0!
#189
b11 5
1!
#190
0!
#191
0'
b0 5
1!
#192
0!
#193
b1 5
1!
#194
0!
#195
b100 :
b11 =
1'
b10 5
1!
#196
0!
#197
b11 5
1!
#198
0!
#199
0'
b0 5
1!
#200
0!
#201
b1 5
1!
#202
0!
#203
b101 :
b10 =
1'
b10 5
1!
#204
0!
#205
b11 5
1!
#206
0!
#207
0'
b0 5
1!
#208
0!
#209
b1 5
1!
#210
0!
#211
b110 :
b1 =
1'
b10 5
1!
#212
0!
#213
b11 5
1!
#214
0!
#215
0'
b0 5
1!
#216
0!
#217
b1 5
1!
#218
0!
#219
b111 :
b0 =
1'
b10 5
1!
#220
0!
#221
b11 5
1!
#222
0!
#223
0'
b0 5
1!
#224
0!
#225
b1 5
1!
#226
0!
#227
b1000 :
b11111111111111111111111111111111 =
1'
b10 5
1!
#228
0!
#229
b11 5
1!
#230
0!
#231
0'
b0 5
1!
#232
0!
#233
b1 5
1!
#234
0!
#235
b1001 :
0$
0%
1'
b10 5
1!
#236
0!
#237
01
00
b11 5
1!
#238
b100000 6
0!
1&
#239
0'
x4
x3
x2
b1 6
b0 :
b0 9
b0 8
b111 =
b1111 <
b110 ;
1$
11
b0 5
b1 7
1!
#240
0!
0&
#241
10
b1 5
1!
#242
0!
#243
1'
b10 5
1!
#244
0!
#245
b11 5
1!
#246
0!
#247
0'
b0 5
1!
#248
0!
#249
b1 5
1!
#250
0!
#251
1'
b10 5
1!
#252
0!
#253
b11 5
1!
#254
0!
#255
0'
b0 5
1!
#256
0!
#257
b1 5
1!
#258
0!
#259
1'
b10 5
1!
#260
0!
b101 ,
1(
#261
b11 5
1!
#262
0!
#263
0'
b0 5
1!
#264
0!
#265
b1 5
1!
#266
0!
#267
1'
b10 5
1!
#268
0!
#269
b11 5
1!
#270
0!
#271
0'
b0 5
1!
#272
0!
#273
b1 5
1!
#274
0!
#275
1'
b10 5
1!
#276
0!
#277
b11 5
1!
#278
0!
#279
0'
b0 5
1!
#280
0!
#281
b1 5
1!
#282
0!
#283
b10 6
1'
01
00
b10 5
0$
1!
1#
#284
0!
0#
#285
b100 6
12
11
b11 5
b10 7
1!
#286
0!
#287
0'
b0 5
b100 7
1!
#288
0!
#289
b1 5
1!
#290
0!
#291
b1 8
b101 ;
1%
1'
b10 5
1!
#292
0!
#293
b11 5
1!
#294
0!
#295
0'
b0 5
1!
#296
0!
#297
b1 5
1!
#298
0!
#299
b10 8
b100 ;
1'
b10 5
1!
#300
0!
#301
b11 5
1!
#302
0!
#303
0'
b0 5
1!
#304
0!
#305
b1 5
1!
#306
0!
#307
b11 8
b11 ;
1'
b10 5
1!
#308
0!
#309
b11 5
1!
#310
0!
#311
0'
b0 5
1!
#312
0!
#313
b1 5
1!
#314
0!
#315
b100 8
b10 ;
1'
b10 5
1!
#316
0!
#317
b11 5
1!
#318
0!
#319
0'
b0 5
1!
#320
0!
#321
b1 5
1!
#322
0!
#323
b101 8
b1 ;
1$
1'
b10 5
1!
#324
0!
#325
10
b11 5
1!
#326
0!
#327
0'
b0 5
1!
#328
0!
#329
b1 5
1!
#330
0!
#331
b110 8
b0 ;
0$
1'
b10 5
1!
#332
0!
#333
01
00
b11 5
1!
#334
0!
#335
0'
11
b0 5
1!
#336
0!
#337
b1 5
1!
#338
0!
#339
b111 8
b11111111111111111111111111111111 ;
1$
1'
b10 5
1!
#340
0!
#341
10
b11 5
1!
#342
0!
#343
0'
b0 5
1!
#344
0!
#345
b1 5
1!
#346
0!
#347
b1000 6
b1000 8
0$
0%
1'
b10 5
1!
#348
0!
#349
13
01
00
b11 5
b1000 7
b10000 6
1!
1&
#350
0!
#351
0'
11
b0 5
b1000 6
1!
0&
#352
0!
#353
b1 5
1!
#354
0!
#355
b1001 8
1'
b10 5
1!
#356
0!
#357
b11 5
1!
#358
0!
#359
0'
b0 5
1!
#360
0!
#361
b1 5
1!
#362
0!
#363
bx0 *
bx0 /
bx0 >
b1 9
1'
b10 5
1!
#364
0!
#365
b11 5
1!
#366
0!
#367
0'
b0 5
1!
#368
0!
#369
b1 5
1!
#370
0!
#371
bx00 *
bx00 /
bx00 >
b10 9
1'
b10 5
1!
#372
0!
#373
b11 5
1!
#374
0!
#375
0'
b0 5
1!
#376
0!
#377
b1 5
b10000 7
b10000 6
1!
1&
#378
0!
#379
bx100 *
bx100 /
bx100 >
b11 9
1'
b10 5
1!
#380
0!
#381
b11 5
1!
#382
0!
#383
0'
b0 5
1!
#384
0!
#385
b1 5
1!
#386
0!
#387
bx0100 *
bx0100 /
bx0100 >
b100 9
1'
b10 5
1!
0&
#388
0!
#389
b11 5
1!
#390
0!
#391
0'
b0 5
1!
#392
0!
#393
b1 5
1!
#394
0!
#395
bx00100 *
bx00100 /
bx00100 >
b101 9
1'
b10 5
1!
#396
0!
#397
b11 5
1!
#398
0!
#399
0'
b0 5
1!
#400
0!
#401
b1 5
1!
#402
0!
#403
bx000100 *
bx000100 /
bx000100 >
b110 9
1'
b10 5
1!
#404
0!
#405
b11 5
1!
#406
0!
#407
0'
b0 5
1!
#408
0!
#409
b1 5
1!
#410
0!
#411
bx0000100 *
bx0000100 /
bx0000100 >
b111 9
1'
b10 5
1!
#412
0!
#413
b11 5
1!
#414
0!
#415
0'
b0 5
1!
#416
0!
#417
b1 5
1!
#418
0!
#419
bx00000100 *
bx00000100 /
bx00000100 >
1$
b100000 6
14
b1000 9
1'
b10 5
1!
#420
0!
#421
10
b11 5
b100000 7
1!
#422
0!
#423
0'
b0 5
1!
#424
0!
#425
b1 5
1!
#426
0!
#427
bx000000100 *
bx000000100 /
bx000000100 >
b1001 9
0$
1'
b10 5
1!
#428
0!
#429
01
00
b11 5
1!
#430
0!
1&
#431
0'
11
b0 5
1!
#432
0!
0&
#433
b1 5
1!
#434
0!
#435
bx0000000100 *
bx0000000100 /
bx0000000100 >
b1010 9
1'
b10 5
1!
#436
0!
#437
b11 5
1!
#438
0!
#439
0'
b0 5
1!
#440
0!
#441
b1 5
1!
#442
0!
#443
bx00000000100 *
bx00000000100 /
bx00000000100 >
b1011 9
1'
b10 5
1!
#444
0!
#445
b11 5
1!
#446
0!
#447
0'
b0 5
1!
#448
0!
#449
b1 5
1!
#450
0!
#451
bx000000000100 *
bx000000000100 /
bx000000000100 >
b1100 9
1'
b10 5
1!
#452
0!
#453
b11 5
1!
#454
0!
#455
0'
b0 5
1!
#456
0!
#457
b1 5
1!
#458
0!
#459
bx0000000000100 *
bx0000000000100 /
bx0000000000100 >
b1101 9
1'
b10 5
1!
#460
0!
#461
b11 5
1!
#462
0!
#463
0'
b0 5
1!
#464
0!
#465
b1 5
1!
#466
0!
#467
bx00000000000100 *
bx00000000000100 /
bx00000000000100 >
b1110 9
1'
b10 5
1!
#468
0!
#469
b11 5
1!
#470
0!
#471
0'
b0 5
1!
#472
0!
#473
b1 5
1!
#474
0!
#475
bx000000000000100 *
bx000000000000100 /
bx000000000000100 >
b1111 9
1'
b10 5
1!
#476
0!
#477
b11 5
1!
#478
0!
#479
0'
b0 5
1!
#480
0!
#481
b1 5
1!
#482
0!
#483
b100 *
b100 /
b100 >
b10000 9
1'
b10 5
1!
#484
0!
#485
b11 5
1!
#486
0!
#487
0'
b0 5
1!
#488
0!
#489
b1 5
1!
#490
0!
#491
bx *
bx /
bx >
x4
x3
x2
b1 6
b1 7
b0 8
b110 ;
1$
b0 9
1'
b10 5
1!
#492
0!
#493
10
b11 5
1!
#494
0!
#495
0'
b0 5
1!
#496
0!
#497
b1 5
1!
#498
0!
#499
1'
b10 5
1!
#500
0!
#501
b11 5
1!
#502
0!
#503
0'
b0 5
1!
#504
0!
#505
b1 5
1!
#506
0!
#507
1'
b10 5
1!
#508
0!
#509
b11 5
1!
#510
0!
#511
0'
b0 5
1!
#512
0!
#513
b1 5
1!
#514
0!
#515
1'
b10 5
1!
#516
0!
#517
b11 5
1!
#518
0!
#519
0'
b0 5
1!
#520
0!
#521
b1 5
1!
#522
0!
#523
1'
b10 5
1!
#524
0!
#525
b11 5
1!
#526
0!
#527
0'
b0 5
1!
#528
0!
#529
b1 5
1!
#530
0!
#531
1'
b10 5
1!
#532
0!
1&
#533
b11 5
1!
#534
0!
0&
#535
0'
b0 5
1!
#536
0!
#537
b1 5
1!
#538
0!
#539
1'
b10 5
1!
#540
0!
#541
b11 5
1!
#542
0!
#543
0'
b0 5
1!
#544
0!
#545
b1 5
1!
#546
0!
#547
1'
b10 5
1!
#548
0!
#549
b11 5
1!
#550
0!
#551
0'
b0 5
1!
#552
0!
#553
b1 5
1!
#554
0!
#555
b10 6
1'
01
00
b10 5
0$
1!
1#
#556
0!
0#
#557
b100 6
12
11
b11 5
b10 7
1!
#558
0!
#559
0'
b0 5
b100 7
1!
#560
0!
#561
b1 5
1!
#562
0!
#563
b1 8
b101 ;
1%
1'
b10 5
1!
#564
0!
#565
b11 5
1!
#566
0!
#567
0'
b0 5
1!
#568
0!
#569
b1 5
1!
#570
0!
#571
b10 8
b100 ;
1'
b10 5
1!
#572
0!
#573
b11 5
1!
#574
0!
#575
0'
b0 5
1!
#576
0!
#577
b1 5
1!
#578
0!
#579
b11 8
b11 ;
1'
b10 5
1!
#580
0!
#581
b11 5
1!
#582
0!
#583
0'
b0 5
1!
#584
0!
#585
b1 5
1!
#586
0!
#587
b100 8
b10 ;
1'
b10 5
1!
#588
0!
#589
b11 5
1!
#590
0!
#591
0'
b0 5
1!
#592
0!
#593
b1 5
1!
#594
0!
#595
b101 8
b1 ;
1$
1'
b10 5
1!
#596
0!
#597
10
b11 5
1!
#598
0!
#599
0'
b0 5
1!
#600
0!
#601
b1 5
1!
#602
0!
#603
b110 8
b0 ;
0$
1'
b10 5
1!
#604
0!
#605
01
00
b11 5
1!
#606
0!
#607
0'
11
b0 5
1!
#608
0!
#609
b1 5
1!
#610
0!
#611
b111 8
b11111111111111111111111111111111 ;
1$
1'
b10 5
1!
#612
0!
#613
10
b11 5
1!
#614
0!
#615
0'
b0 5
1!
#616
0!
#617
b1 5
1!
#618
0!
#619
b1000 6
b1000 8
0$
0%
1'
b10 5
1!
#620
0!
#621
13
01
00
b11 5
b1000 7
b10000 6
1!
1&
#622
0!
#623
0'
11
b0 5
b1000 6
1!
0&
#624
0!
#625
b1 5
1!
#626
0!
#627
b1001 8
1'
b10 5
1!
#628
0!
#629
b11 5
1!
#630
0!
#631
0'
b0 5
1!
#632
0!
#633
b1 5
1!
#634
0!
#635
bx0 *
bx0 /
bx0 >
b1 9
1'
b10 5
1!
#636
0!
#637
b11 5
1!
#638
0!
#639
0'
b0 5
1!
#640
0!
#641
b1 5
1!
#642
0!
#643
bx00 *
bx00 /
bx00 >
b10 9
1'
b10 5
1!
#644
0!
#645
b11 5
1!
#646
0!
#647
0'
b0 5
1!
#648
0!
#649
b1 5
b10000 7
b10000 6
1!
1&
#650
0!
#651
bx100 *
bx100 /
bx100 >
b11 9
1'
b10 5
1!
#652
0!
#653
b11 5
1!
#654
0!
#655
0'
b0 5
1!
#656
0!
#657
b1 5
1!
#658
0!
#659
bx0100 *
bx0100 /
bx0100 >
b100 9
1'
b10 5
1!
0&
#660
0!
#661
b11 5
1!
#662
0!
#663
0'
b0 5
1!
#664
0!
#665
b1 5
1!
#666
0!
#667
bx00100 *
bx00100 /
bx00100 >
b101 9
1'
b10 5
1!
#668
0!
#669
b11 5
1!
#670
0!
#671
0'
b0 5
1!
#672
0!
#673
b1 5
1!
#674
0!
#675
bx000100 *
bx000100 /
bx000100 >
b110 9
1'
b10 5
1!
#676
0!
#677
b11 5
1!
#678
0!
#679
0'
b0 5
1!
#680
0!
#681
b1 5
1!
#682
0!
#683
bx0000100 *
bx0000100 /
bx0000100 >
b111 9
1'
b10 5
1!
#684
0!
#685
b11 5
1!
#686
0!
#687
0'
b0 5
1!
#688
0!
#689
b1 5
1!
#690
0!
#691
bx00000100 *
bx00000100 /
bx00000100 >
1$
b100000 6
14
b1000 9
1'
b10 5
1!
#692
0!
#693
10
b11 5
b100000 7
1!
#694
0!
#695
0'
b0 5
1!
#696
0!
#697
b1 5
1!
#698
0!
#699
bx000000100 *
bx000000100 /
bx000000100 >
b1001 9
0$
1'
b10 5
1!
#700
0!
#701
01
00
b11 5
1!
#702
0!
1&
#703
0'
11
b0 5
1!
#704
0!
0&
#705
b1 5
1!
#706
0!
#707
bx0000000100 *
bx0000000100 /
bx0000000100 >
b1010 9
1'
b10 5
1!
#708
0!
#709
b11 5
1!
#710
0!
#711
0'
b0 5
1!
#712
0!
#713
b1 5
1!
#714
0!
#715
bx00000000100 *
bx00000000100 /
bx00000000100 >
b1011 9
1'
b10 5
1!
#716
0!
#717
b11 5
1!
#718
0!
#719
0'
b0 5
1!
#720
0!
#721
b1 5
1!
#722
0!
#723
bx000000000100 *
bx000000000100 /
bx000000000100 >
b1100 9
1'
b10 5
1!
#724
0!
#725
b11 5
1!
#726
0!
#727
0'
b0 5
1!
#728
0!
#729
b1 5
1!
#730
0!
#731
bx0000000000100 *
bx0000000000100 /
bx0000000000100 >
b1101 9
1'
b10 5
1!
#732
0!
#733
b11 5
1!
#734
0!
0)
#735
1$
bx *
bx /
bx >
b100000 6
x4
x3
x2
b0 9
b0 8
b110 ;
1!
#736
0!
#737
b1 6
1!
#738
0!
#739
1!
#740
0!
#741
1!
#742
0!
#743
1!
#744
0!
1)
#745
0'
10
b0 5
b1 7
1!
#746
0!
#747
b1 5
1!
#748
0!
#749
1'
b10 5
1!
#750
0!
#751
b11 5
1!
#752
0!
#753
0'
b0 5
1!
#754
0!
#755
b1 5
1!
#756
0!
#757
1'
b10 5
1!
#758
0!
#759
b11 5
1!
#760
0!
#761
0'
b0 5
1!
#762
0!
#763
b1 5
1!
#764
0!
#765
1'
b10 5
1!
#766
0!
#767
b11 5
1!
#768
0!
#769
0'
b0 5
1!
#770
0!
#771
b1 5
1!
#772
0!
#773
1'
b10 5
1!
